Workbook

Sheet Input Costs
A1: COST INPUTS DATABASE
A2: Last Updated: | B2: =TODAY() -> 46062
A3: Currency Base: | B3: INR
A5: EXCHANGE RATES
A6: USD/INR | B6: 91.59
A7: EUR/INR | B7: 108.44
A8: CAD/INR | B8: 66.88
A9: GBP/INR | B9: 125.06
A11: CONVERTING COSTS (per MT) | B11: INR | C11: USD | D11: EUR | E11: CAD | F11: GBP
A12: Direct Labor | B12: 6500 | C12: =B12/$B$6 -> 70.968446 | D12: =B12/$B$7 -> 59.940981 | E12: =B12/$B$8 -> 97.188995 | F12: =B12/$B$9 -> 51.975052
A13: Power/Electricity | B13: 2500 | C13: =B13/$B$6 -> 27.295556 | D13: =B13/$B$7 -> 23.054224 | E13: =B13/$B$8 -> 37.380383 | F13: =B13/$B$9 -> 19.990405
A14: Cores | B14: 3500 | C14: =B14/$B$6 -> 38.213779 | D14: =B14/$B$7 -> 32.275913 | E14: =B14/$B$8 -> 52.332536 | F14: =B14/$B$9 -> 27.986566
A15: Glue/Adhesive | B15: 800 | C15: =B15/$B$6 -> 8.734578 | D15: =B15/$B$7 -> 7.3773515 | E15: =B15/$B$8 -> 11.961722 | F15: =B15/$B$9 -> 6.3969295
A16: Machine Maintenance | B16: 2500 | C16: =B16/$B$6 -> 27.295556 | D16: =B16/$B$7 -> 23.054224 | E16: =B16/$B$8 -> 37.380383 | F16: =B16/$B$9 -> 19.990405
A17: Consumables (blades, etc.) | B17: 1000 | C17: =B17/$B$6 -> 10.918223 | D17: =B17/$B$7 -> 9.2216894 | E17: =B17/$B$8 -> 14.952153 | F17: =B17/$B$9 -> 7.9961618
A18: TOTAL CONVERTING/MT | B18: =SUM(B12:B17) -> 16800 | C18: =B18/$B$6 -> 183.42614 | D18: =B18/$B$7 -> 154.92438 | E18: =B18/$B$8 -> 251.19617 | F18: =B18/$B$9 -> 134.33552
A20: PACKAGING MATERIALS | B20: INR | C20: Unit
A21: Printed Poly Film | B21: 220 | C21: per kg
A22: Plain Poly Film | B22: 170 | C22: per kg
A23: Paper Wrap | B23: 120 | C23: per kg
A24: Average Carton Cost | B24: 40 | C24: each
A25: Tape per Carton | B25: 3 | C25: each
A26: Labels per Carton | B26: 2 | C26: each
A27: Pallet Cost (wooden) | B27: 500 | C27: each
A28: Stretch Wrap per Pallet | B28: 120 | C28: each
A29: Strapping per Pallet | B29: 50 | C29: each
A31: FILM USAGE (grams per unit) | B31: Grams
A32: Toilet Roll (single wrap) | B32: 3
A33: Toilet Roll (multipack) | B33: 8
A34: Kitchen Towel (AFH) | B34: 12
A35: Napkin Pack | B35: 5
A37: OVERHEAD COSTS (Monthly) | B37: INR
A38: Factory Rent/Lease | B38: 150000
A39: Admin Salaries | B39: 200000
A40: Utilities (non-production) | B40: 50000
A41: Quality Control | B41: 75000
A42: Insurance | B42: 40000
A43: Depreciation | B43: 100000
A44: Other Overhead | B44: 50000
A45: TOTAL MONTHLY OVERHEAD | B45: =SUM(B38:B44) -> 665000
A46: Monthly Output (MT) | B46: 100
A47: OVERHEAD PER MT | B47: =B45/B46 -> 6650
A49: WASTE FACTORS | B49: %
A50: Trim Waste | B50: 0.03
A51: Startup Waste | B51: 0.015
A52: Reject Rate | B52: 0.01
A53: TOTAL LOSS FACTOR | B53: =SUM(B50:B52) -> 0.055
A54: GROSS-UP MULTIPLIER | B54: =1+B53 -> 1.055
A55: Waste Recovery Value | B55: 20 | C55: INR/kg
A57: LOCAL LOGISTICS (per shipment) | B57: INR | C57: USD | D57: EUR | E57: CAD | F57: GBP
A58: Factory to Port (per container) | B58: 35000 | C58: =B58/$B$6 -> 382.13779 | D58: =B58/$B$7 -> 322.75913 | E58: =B58/$B$8 -> 523.32536 | F58: =B58/$B$9 -> 279.86566
A59: Port Handling (per container) | B59: 25000 | C59: =B59/$B$6 -> 272.95556 | D59: =B59/$B$7 -> 230.54224 | E59: =B59/$B$8 -> 373.80383 | F59: =B59/$B$9 -> 199.90405
A60: Documentation (per shipment) | B60: 15000 | C60: =B60/$B$6 -> 163.77334 | D60: =B60/$B$7 -> 138.32534 | E60: =B60/$B$8 -> 224.2823 | F60: =B60/$B$9 -> 119.94243
A61: Export Customs (per shipment) | B61: 10000 | C61: =B61/$B$6 -> 109.18223 | D61: =B61/$B$7 -> 92.216894 | E61: =B61/$B$8 -> 149.52153 | F61: =B61/$B$9 -> 79.961618
A62: Phytosanitary Certificate | B62: 5000 | C62: =B62/$B$6 -> 54.591113 | D62: =B62/$B$7 -> 46.108447 | E62: =B62/$B$8 -> 74.760766 | F62: =B62/$B$9 -> 39.980809
A64: OCEAN FREIGHT (USD per 40HC) | B64: USD
A65: USA - East Coast | B65: 3500
A66: USA - West Coast | B66: 2800
A67: Canada - Vancouver | B67: 3000
A68: Canada - Toronto | B68: 4000
A69: Europe - Rotterdam | B69: 2200
A70: Europe - Hamburg | B70: 2400
A71: UK - Felixstowe | B71: 2600
A72: Middle East - Dubai | B72: 1200
A73: Australia - Melbourne | B73: 2000
A75: INSURANCE & OTHER
A76: Marine Insurance Rate | B76: 0.004 | C76: of FOB
A77: Margin - Minimum | B77: 0.1
A78: Margin - Standard | B78: 0.15
A79: Margin - Target | B79: 0.2
A80: Margin - Premium | B80: 0.25

Sheet Input Reels
A1: Product_Description | B1: Reel_Code | C1: Supplier | D1: Ply | E1: GSM_Per_Ply | F1: Total_GSM | G1: Virgin_Pct | H1: Wet_Strength | I1: Color | J1: Softness | K1: Width_mm | L1: Dia_mm | M1: Price_INR_MT | N1: Price_USD_MT | O1: Lead_Days | P1: MOQ_MT | Q1: Last_Updated | R1: Notes
A2: VIRGIN WHITE SOFTNESS STANDARD | B2: R-1P-13-V | C2: Supplier A | D2: 1 | E2: 13 | F2: =D2*E2 -> 13 | G2: 1 | H2: No | I2: White | J2: Standard | K2: 2800 | L2: 1500 | M2: 112000 | N2: =M2/'Input Costs'!$B$6 -> 1222.8409 | O2: 21 | P2: 5 | Q2: =TODAY() -> 46062 | R2: Ultra light tissue
B3: R-1P-14-V | C3: Supplier A | D3: 1 | E3: 14 | F3: =D3*E3 -> 14 | G3: 1 | H3: No | I3: White | J3: Standard | K3: 2800 | L3: 1500 | M3: 108000 | N3: =M3/'Input Costs'!$B$6 -> 1179.168 | O3: 21 | P3: 5 | Q3: =TODAY() -> 46062 | R3: Light facial tissue
B4: R-1P-15-V | C4: Supplier A | D4: 1 | E4: 15 | F4: =D4*E4 -> 15 | G4: 1 | H4: No | I4: White | J4: Standard | K4: 2800 | L4: 1500 | M4: 105000 | N4: =M4/'Input Costs'!$B$6 -> 1146.4134 | O4: 21 | P4: 5 | Q4: =TODAY() -> 46062 | R4: Standard facial
B5: R-1P-16-V | C5: Supplier A | D5: 1 | E5: 16 | F5: =D5*E5 -> 16 | G5: 1 | H5: No | I5: White | J5: Standard | K5: 2800 | L5: 1500 | M5: 103000 | N5: =M5/'Input Costs'!$B$6 -> 1124.5769 | O5: 21 | P5: 5 | Q5: =TODAY() -> 46062 | R5: Light toilet tissue
B6: R-1P-17-V | C6: Supplier A | D6: 1 | E6: 17 | F6: =D6*E6 -> 17 | G6: 1 | H6: No | I6: White | J6: Standard | K6: 2800 | L6: 1500 | M6: 102000 | N6: =M6/'Input Costs'!$B$6 -> 1113.6587 | O6: 21 | P6: 5 | Q6: =TODAY() -> 46062 | R6: Standard toilet
B7: R-1P-18-V | C7: Supplier A | D7: 1 | E7: 18 | F7: =D7*E7 -> 18 | G7: 1 | H7: No | I7: White | J7: Standard | K7: 2800 | L7: 1500 | M7: 100000 | N7: =M7/'Input Costs'!$B$6 -> 1091.8223 | O7: 21 | P7: 5 | Q7: =TODAY() -> 46062 | R7: Standard napkin
B8: R-1P-19-V | C8: Supplier A | D8: 1 | E8: 19 | F8: =D8*E8 -> 19 | G8: 1 | H8: No | I8: White | J8: Standard | K8: 2800 | L8: 1500 | M8: 98000 | N8: =M8/'Input Costs'!$B$6 -> 1069.9858 | O8: 21 | P8: 5 | Q8: =TODAY() -> 46062 | R8: Medium weight
B9: R-1P-20-V | C9: Supplier A | D9: 1 | E9: 20 | F9: =D9*E9 -> 20 | G9: 1 | H9: No | I9: White | J9: Standard | K9: 2800 | L9: 1500 | M9: 97000 | N9: =M9/'Input Costs'!$B$6 -> 1059.0676 | O9: 21 | P9: 5 | Q9: =TODAY() -> 46062 | R9: Kitchen towel base
B10: R-1P-21-V | C10: Supplier A | D10: 1 | E10: 21 | F10: =D10*E10 -> 21 | G10: 1 | H10: No | I10: White | J10: Standard | K10: 2800 | L10: 1500 | M10: 96000 | N10: =M10/'Input Costs'!$B$6 -> 1048.1494 | O10: 21 | P10: 5 | Q10: =TODAY() -> 46062 | R10: Medium KT
B11: R-1P-22-V | C11: Supplier A | D11: 1 | E11: 22 | F11: =D11*E11 -> 22 | G11: 1 | H11: No | I11: White | J11: Standard | K11: 2800 | L11: 1500 | M11: 95000 | N11: =M11/'Input Costs'!$B$6 -> 1037.2311 | O11: 21 | P11: 5 | Q11: =TODAY() -> 46062 | R11: Standard KT
B12: R-1P-23-V | C12: Supplier A | D12: 1 | E12: 23 | F12: =D12*E12 -> 23 | G12: 1 | H12: No | I12: White | J12: Standard | K12: 2800 | L12: 1500 | M12: 94000 | N12: =M12/'Input Costs'!$B$6 -> 1026.3129 | O12: 21 | P12: 5 | Q12: =TODAY() -> 46062 | R12: Heavy KT
B13: R-1P-24-V | C13: Supplier A | D13: 1 | E13: 24 | F13: =D13*E13 -> 24 | G13: 1 | H13: No | I13: White | J13: Standard | K13: 2800 | L13: 1500 | M13: 93000 | N13: =M13/'Input Costs'!$B$6 -> 1015.3947 | O13: 21 | P13: 5 | Q13: =TODAY() -> 46062 | R13: Industrial base
B14: R-1P-25-V | C14: Supplier A | D14: 1 | E14: 25 | F14: =D14*E14 -> 25 | G14: 1 | H14: No | I14: White | J14: Standard | K14: 2800 | L14: 1500 | M14: 92000 | N14: =M14/'Input Costs'!$B$6 -> 1004.4765 | O14: 21 | P14: 5 | Q14: =TODAY() -> 46062 | R14: Heavy duty
... B16: R-1P-30-V | C16: Supplier A | D16: 1 | E16: 30 | F16: =D16*E16 -> 30 | G16: 1 | H16: No | I16: White | J16: Standard | K16: 2800 | L16: 1500 | M16: 88000 | N16: =M16/'Input Costs'!$B$6 -> 960.80358 | O16: 21 | P16: 5 | Q16: =TODAY() -> 46062 | R16: Wiper base
A17: VIRGIN WHITE SOFTNESS PREMIUM | B17: R-1P-13-VP | C17: Supplier A | D17: 1 | E17: 13 | F17: =D17*E17 -> 13 | G17: 1 | H17: No | I17: White | J17: Premium | K17: 2800 | L17: 1500 | M17: 125000 | N17: =M17/'Input Costs'!$B$6 -> 1364.7778 | O17: 25 | P17: 5 | Q17: =TODAY() -> 46062 | R17: Premium facial
B18: R-1P-14-VP | C18: Supplier A | D18: 1 | E18: 14 | F18: =D18*E18 -> 14 | G18: 1 | H18: No | I18: White | J18: Premium | K18: 2800 | L18: 1500 | M18: 122000 | N18: =M18/'Input Costs'!$B$6 -> 1332.0231 | O18: 25 | P18: 5 | Q18: =TODAY() -> 46062 | R18: Premium facial
B19: R-1P-15-VP | C19: Supplier A | D19: 1 | E19: 15 | F19: =D19*E19 -> 15 | G19: 1 | H19: No | I19: White | J19: Premium | K19: 2800 | L19: 1500 | M19: 118000 | N19: =M19/'Input Costs'!$B$6 -> 1288.3503 | O19: 25 | P19: 5 | Q19: =TODAY() -> 46062 | R19: Premium toilet
B20: R-1P-16-VP | C20: Supplier A | D20: 1 | E20: 16 | F20: =D20*E20 -> 16 | G20: 1 | H20: No | I20: White | J20: Premium | K20: 2800 | L20: 1500 | M20: 116000 | N20: =M20/'Input Costs'!$B$6 -> 1266.5138 | O20: 25 | P20: 5 | Q20: =TODAY() -> 46062 | R20: Premium toilet
B21: R-1P-17-VP | C21: Supplier A | D21: 1 | E21: 17 | F21: =D21*E21 -> 17 | G21: 1 | H21: No | I21: White | J21: Premium | K21: 2800 | L21: 1500 | M21: 115000 | N21: =M21/'Input Costs'!$B$6 -> 1255.5956 | O21: 25 | P21: 5 | Q21: =TODAY() -> 46062 | R21: Luxury toilet
B22: R-1P-18-VP | C22: Supplier A | D22: 1 | E22: 18 | F22: =D22*E22 -> 18 | G22: 1 | H22: No | I22: White | J22: Premium | K22: 2800 | L22: 1500 | M22: 113000 | N22: =M22/'Input Costs'!$B$6 -> 1233.7591 | O22: 25 | P22: 5 | Q22: =TODAY() -> 46062 | R22: Premium napkin
B23: R-1P-20-VP | C23: Supplier A | D23: 1 | E23: 20 | F23: =D23*E23 -> 20 | G23: 1 | H23: No | I23: White | J23: Premium | K23: 2800 | L23: 1500 | M23: 110000 | N23: =M23/'Input Costs'!$B$6 -> 1201.0045 | O23: 25 | P23: 5 | Q23: =TODAY() -> 46062 | R23: Premium KT
B24: R-1P-22-VP | C24: Supplier A | D24: 1 | E24: 22 | F24: =D24*E24 -> 22 | G24: 1 | H24: No | I24: White | J24: Premium | K24: 2800 | L24: 1500 | M24: 108000 | N24: =M24/'Input Costs'!$B$6 -> 1179.168 | O24: 25 | P24: 5 | Q24: =TODAY() -> 46062 | R24: Premium KT
A25: VIRGIN WHITE SOFTNESS ECONOMY | B25: R-1P-15-VE | C25: Supplier A | D25: 1 | E25: 15 | F25: =D25*E25 -> 15 | G25: 1 | H25: No | I25: White | J25: Economy | K25: 2800 | L25: 1500 | M25: 98000 | N25: =M25/'Input Costs'!$B$6 -> 1069.9858 | O25: 21 | P25: 10 | Q25: =TODAY() -> 46062 | R25: Budget toilet
B26: R-1P-17-VE | C26: Supplier A | D26: 1 | E26: 17 | F26: =D26*E26 -> 17 | G26: 1 | H26: No | I26: White | J26: Economy | K26: 2800 | L26: 1500 | M26: 95000 | N26: =M26/'Input Costs'!$B$6 -> 1037.2311 | O26: 21 | P26: 10 | Q26: =TODAY() -> 46062 | R26: Budget toilet
B27: R-1P-18-VE | C27: Supplier A | D27: 1 | E27: 18 | F27: =D27*E27 -> 18 | G27: 1 | H27: No | I27: White | J27: Economy | K27: 2800 | L27: 1500 | M27: 93000 | N27: =M27/'Input Costs'!$B$6 -> 1015.3947 | O27: 21 | P27: 10 | Q27: =TODAY() -> 46062 | R27: Budget napkin
B28: R-1P-20-VE | C28: Supplier A | D28: 1 | E28: 20 | F28: =D28*E28 -> 20 | G28: 1 | H28: No | I28: White | J28: Economy | K28: 2800 | L28: 1500 | M28: 90000 | N28: =M28/'Input Costs'!$B$6 -> 982.64003 | O28: 21 | P28: 10 | Q28: =TODAY() -> 46062 | R28: Budget KT
B29: R-1P-22-VE | C29: Supplier A | D29: 1 | E29: 22 | F29: =D29*E29 -> 22 | G29: 1 | H29: No | I29: White | J29: Economy | K29: 2800 | L29: 1500 | M29: 88000 | N29: =M29/'Input Costs'!$B$6 -> 960.80358 | O29: 21 | P29: 10 | Q29: =TODAY() -> 46062 | R29: Budget KT
A30: MIXED FIBER WHITE (VIRGIN + RECYCLED) | B30: R-1P-15-M80 | C30: Supplier A | D30: 1 | E30: 15 | F30: =D30*E30 -> 15 | G30: 0.8 | H30: No | I30: White | J30: Standard | K30: 2800 | L30: 1500 | M30: 95000 | N30: =M30/'Input Costs'!$B$6 -> 1037.2311 | O30: 21 | P30: 5 | Q30: =TODAY() -> 46062 | R30: 80% virgin blend
B31: R-1P-17-M80 | C31: Supplier A | D31: 1 | E31: 17 | F31: =D31*E31 -> 17 | G31: 0.8 | H31: No | I31: White | J31: Standard | K31: 2800 | L31: 1500 | M31: 93000 | N31: =M31/'Input Costs'!$B$6 -> 1015.3947 | O31: 21 | P31: 5 | Q31: =TODAY() -> 46062 | R31: 80% virgin blend
B32: R-1P-18-M80 | C32: Supplier A | D32: 1 | E32: 18 | F32: =D32*E32 -> 18 | G32: 0.8 | H32: No | I32: White | J32: Standard | K32: 2800 | L32: 1500 | M32: 91000 | N32: =M32/'Input Costs'!$B$6 -> 993.55825 | O32: 21 | P32: 5 | Q32: =TODAY() -> 46062 | R32: 80% virgin blend
B33: R-1P-20-M80 | C33: Supplier A | D33: 1 | E33: 20 | F33: =D33*E33 -> 20 | G33: 0.8 | H33: No | I33: White | J33: Standard | K33: 2800 | L33: 1500 | M33: 89000 | N33: =M33/'Input Costs'!$B$6 -> 971.7218 | O33: 21 | P33: 5 | Q33: =TODAY() -> 46062 | R33: 80% virgin blend
B34: R-1P-22-M80 | C34: Supplier A | D34: 1 | E34: 22 | F34: =D34*E34 -> 22 | G34: 0.8 | H34: No | I34: White | J34: Standard | K34: 2800 | L34: 1500 | M34: 87000 | N34: =M34/'Input Costs'!$B$6 -> 949.88536 | O34: 21 | P34: 5 | Q34: =TODAY() -> 46062 | R34: 80% virgin blend
B35: R-1P-15-M70 | C35: Supplier A | D35: 1 | E35: 15 | F35: =D35*E35 -> 15 | G35: 0.7 | H35: No | I35: White | J35: Standard | K35: 2800 | L35: 1500 | M35: 90000 | N35: =M35/'Input Costs'!$B$6 -> 982.64003 | O35: 21 | P35: 5 | Q35: =TODAY() -> 46062 | R35: 70% virgin blend
B36: R-1P-17-M70 | C36: Supplier A | D36: 1 | E36: 17 | F36: =D36*E36 -> 17 | G36: 0.7 | H36: No | I36: White | J36: Standard | K36: 2800 | L36: 1500 | M36: 88000 | N36: =M36/'Input Costs'!$B$6 -> 960.80358 | O36: 21 | P36: 5 | Q36: =TODAY() -> 46062 | R36: 70% virgin blend
B37: R-1P-18-M70 | C37: Supplier A | D37: 1 | E37: 18 | F37: =D37*E37 -> 18 | G37: 0.7 | H37: No | I37: White | J37: Standard | K37: 2800 | L37: 1500 | M37: 86000 | N37: =M37/'Input Costs'!$B$6 -> 938.96714 | O37: 21 | P37: 5 | Q37: =TODAY() -> 46062 | R37: 70% virgin blend
B38: R-1P-20-M70 | C38: Supplier A | D38: 1 | E38: 20 | F38: =D38*E38 -> 20 | G38: 0.7 | H38: No | I38: White | J38: Standard | K38: 2800 | L38: 1500 | M38: 84000 | N38: =M38/'Input Costs'!$B$6 -> 917.13069 | O38: 21 | P38: 5 | Q38: =TODAY() -> 46062 | R38: 70% virgin blend
B39: R-1P-22-M70 | C39: Supplier A | D39: 1 | E39: 22 | F39: =D39*E39 -> 22 | G39: 0.7 | H39: No | I39: White | J39: Standard | K39: 2800 | L39: 1500 | M39: 82000 | N39: =M39/'Input Costs'!$B$6 -> 895.29425 | O39: 21 | P39: 5 | Q39: =TODAY() -> 46062 | R39: 70% virgin blend
B40: R-1P-15-M50 | C40: Supplier A | D40: 1 | E40: 15 | F40: =D40*E40 -> 15 | G40: 0.5 | H40: No | I40: White | J40: Standard | K40: 2800 | L40: 1500 | M40: 82000 | N40: =M40/'Input Costs'!$B$6 -> 895.29425 | O40: 21 | P40: 5 | Q40: =TODAY() -> 46062 | R40: 50% virgin blend
B41: R-1P-17-M50 | C41: Supplier A | D41: 1 | E41: 17 | F41: =D41*E41 -> 17 | G41: 0.5 | H41: No | I41: White | J41: Standard | K41: 2800 | L41: 1500 | M41: 80000 | N41: =M41/'Input Costs'!$B$6 -> 873.4578 | O41: 21 | P41: 5 | Q41: =TODAY() -> 46062 | R41: 50% virgin blend
B42: R-1P-18-M50 | C42: Supplier A | D42: 1 | E42: 18 | F42: =D42*E42 -> 18 | G42: 0.5 | H42: No | I42: White | J42: Standard | K42: 2800 | L42: 1500 | M42: 78000 | N42: =M42/'Input Costs'!$B$6 -> 851.62136 | O42: 21 | P42: 5 | Q42: =TODAY() -> 46062 | R42: 50% virgin blend
... B48: R-1P-22-M30 | C48: Supplier A | D48: 1 | E48: 22 | F48: =D48*E48 -> 22 | G48: 0.3 | H48: No | I48: White | J48: Standard | K48: 2800 | L48: 1500 | M48: 66000 | N48: =M48/'Input Costs'!$B$6 -> 720.60269 | O48: 21 | P48: 5 | Q48: =TODAY() -> 46062 | R48: 30% virgin blend
A49: 100% RECYCLED | B49: R-1P-17-R | C49: Supplier A | D49: 1 | E49: 17 | F49: =D49*E49 -> 17 | G49: 0 | H49: No | I49: White | J49: Economy | K49: 2800 | L49: 1500 | M49: 62000 | N49: =M49/'Input Costs'!$B$6 -> 676.9298 | O49: 21 | P49: 10 | Q49: =TODAY() -> 46062 | R49: 100% recycled
B50: R-1P-18-R | C50: Supplier A | D50: 1 | E50: 18 | F50: =D50*E50 -> 18 | G50: 0 | H50: No | I50: White | J50: Economy | K50: 2800 | L50: 1500 | M50: 60000 | N50: =M50/'Input Costs'!$B$6 -> 655.09335 | O50: 21 | P50: 10 | Q50: =TODAY() -> 46062 | R50: 100% recycled
B51: R-1P-20-R | C51: Supplier A | D51: 1 | E51: 20 | F51: =D51*E51 -> 20 | G51: 0 | H51: No | I51: White | J51: Economy | K51: 2800 | L51: 1500 | M51: 58000 | N51: =M51/'Input Costs'!$B$6 -> 633.25691 | O51: 21 | P51: 10 | Q51: =TODAY() -> 46062 | R51: 100% recycled
B52: R-1P-22-R | C52: Supplier A | D52: 1 | E52: 22 | F52: =D52*E52 -> 22 | G52: 0 | H52: No | I52: White | J52: Economy | K52: 2800 | L52: 1500 | M52: 56000 | N52: =M52/'Input Costs'!$B$6 -> 611.42046 | O52: 21 | P52: 10 | Q52: =TODAY() -> 46062 | R52: 100% recycled
B53: R-1P-25-R | C53: Supplier A | D53: 1 | E53: 25 | F53: =D53*E53 -> 25 | G53: 0 | H53: No | I53: White | J53: Economy | K53: 2800 | L53: 1500 | M53: 54000 | N53: =M53/'Input Costs'!$B$6 -> 589.58402 | O53: 21 | P53: 10 | Q53: =TODAY() -> 46062 | R53: 100% recycled
A54: WET STRENGTH VIRGIN | B54: R-1P-18-VW | C54: Supplier A | D54: 1 | E54: 18 | F54: =D54*E54 -> 18 | G54: 1 | H54: Yes | I54: White | J54: Standard | K54: 2800 | L54: 1500 | M54: 115000 | N54: =M54/'Input Costs'!$B$6 -> 1255.5956 | O54: 25 | P54: 5 | Q54: =TODAY() -> 46062 | R54: Wet strength napkin
B55: R-1P-20-VW | C55: Supplier A | D55: 1 | E55: 20 | F55: =D55*E55 -> 20 | G55: 1 | H55: Yes | I55: White | J55: Standard | K55: 2800 | L55: 1500 | M55: 112000 | N55: =M55/'Input Costs'!$B$6 -> 1222.8409 | O55: 25 | P55: 5 | Q55: =TODAY() -> 46062 | R55: Wet strength KT
B56: R-1P-22-VW | C56: Supplier A | D56: 1 | E56: 22 | F56: =D56*E56 -> 22 | G56: 1 | H56: Yes | I56: White | J56: Standard | K56: 2800 | L56: 1500 | M56: 110000 | N56: =M56/'Input Costs'!$B$6 -> 1201.0045 | O56: 25 | P56: 5 | Q56: =TODAY() -> 46062 | R56: Wet strength KT
B57: R-1P-24-VW | C57: Supplier A | D57: 1 | E57: 24 | F57: =D57*E57 -> 24 | G57: 1 | H57: Yes | I57: White | J57: Standard | K57: 2800 | L57: 1500 | M57: 108000 | N57: =M57/'Input Costs'!$B$6 -> 1179.168 | O57: 25 | P57: 5 | Q57: =TODAY() -> 46062 | R57: Wet strength heavy
B58: R-1P-25-VW | C58: Supplier A | D58: 1 | E58: 25 | F58: =D58*E58 -> 25 | G58: 1 | H58: Yes | I58: White | J58: Standard | K58: 2800 | L58: 1500 | M58: 106000 | N58: =M58/'Input Costs'!$B$6 -> 1157.3316 | O58: 25 | P58: 5 | Q58: =TODAY() -> 46062 | R58: Wet strength heavy
B59: R-1P-28-VW | C59: Supplier A | D59: 1 | E59: 28 | F59: =D59*E59 -> 28 | G59: 1 | H59: Yes | I59: White | J59: Standard | K59: 2800 | L59: 1500 | M59: 103000 | N59: =M59/'Input Costs'!$B$6 -> 1124.5769 | O59: 25 | P59: 5 | Q59: =TODAY() -> 46062 | R59: Industrial wiper
B60: R-1P-30-VW | C60: Supplier A | D60: 1 | E60: 30 | F60: =D60*E60 -> 30 | G60: 1 | H60: Yes | I60: White | J60: Standard | K60: 2800 | L60: 1500 | M60: 100000 | N60: =M60/'Input Costs'!$B$6 -> 1091.8223 | O60: 25 | P60: 5 | Q60: =TODAY() -> 46062 | R60: Industrial wiper
B61: R-1P-35-VW | C61: Supplier A | D61: 1 | E61: 35 | F61: =D61*E61 -> 35 | G61: 1 | H61: Yes | I61: White | J61: Standard | K61: 2800 | L61: 1500 | M61: 95000 | N61: =M61/'Input Costs'!$B$6 -> 1037.2311 | O61: 25 | P61: 5 | Q61: =TODAY() -> 46062 | R61: Heavy duty wiper
B62: R-1P-40-VW | C62: Supplier A | D62: 1 | E62: 40 | F62: =D62*E62 -> 40 | G62: 1 | H62: Yes | I62: White | J62: Standard | K62: 2800 | L62: 1500 | M62: 92000 | N62: =M62/'Input Costs'!$B$6 -> 1004.4765 | O62: 25 | P62: 5 | Q62: =TODAY() -> 46062 | R62: Heavy duty wiper
A63: NATURAL / UNBLEACHED | B63: R-1P-15-VN | C63: Supplier A | D63: 1 | E63: 15 | F63: =D63*E63 -> 15 | G63: 1 | H63: No | I63: Natural | J63: Standard | K63: 2800 | L63: 1500 | M63: 100000 | N63: =M63/'Input Costs'!$B$6 -> 1091.8223 | O63: 21 | P63: 5 | Q63: =TODAY() -> 46062 | R63: Unbleached tissue
B64: R-1P-17-VN | C64: Supplier A | D64: 1 | E64: 17 | F64: =D64*E64 -> 17 | G64: 1 | H64: No | I64: Natural | J64: Standard | K64: 2800 | L64: 1500 | M64: 97000 | N64: =M64/'Input Costs'!$B$6 -> 1059.0676 | O64: 21 | P64: 5 | Q64: =TODAY() -> 46062 | R64: Unbleached toilet
B65: R-1P-18-VN | C65: Supplier A | D65: 1 | E65: 18 | F65: =D65*E65 -> 18 | G65: 1 | H65: No | I65: Natural | J65: Standard | K65: 2800 | L65: 1500 | M65: 95000 | N65: =M65/'Input Costs'!$B$6 -> 1037.2311 | O65: 21 | P65: 5 | Q65: =TODAY() -> 46062 | R65: Unbleached napkin
B66: R-1P-20-VN | C66: Supplier A | D66: 1 | E66: 20 | F66: =D66*E66 -> 20 | G66: 1 | H66: No | I66: Natural | J66: Standard | K66: 2800 | L66: 1500 | M66: 92000 | N66: =M66/'Input Costs'!$B$6 -> 1004.4765 | O66: 21 | P66: 5 | Q66: =TODAY() -> 46062 | R66: Unbleached KT
B67: R-1P-22-VNW | C67: Supplier A | D67: 1 | E67: 22 | F67: =D67*E67 -> 22 | G67: 1 | H67: No | I67: Natural | J67: Standard | K67: 2800 | L67: 1500 | M67: 90000 | N67: =M67/'Input Costs'!$B$6 -> 982.64003 | O67: 21 | P67: 5 | Q67: =TODAY() -> 46062 | R67: Unbleached KT
B68: R-1P-17-VNP | C68: Supplier A | D68: 1 | E68: 17 | F68: =D68*E68 -> 17 | G68: 1 | H68: No | I68: Natural | J68: Premium | K68: 2800 | L68: 1500 | M68: 110000 | N68: =M68/'Input Costs'!$B$6 -> 1201.0045 | O68: 25 | P68: 5 | Q68: =TODAY() -> 46062 | R68: Premium unbleached
B69: R-1P-18-VNP | C69: Supplier A | D69: 1 | E69: 18 | F69: =D69*E69 -> 18 | G69: 1 | H69: No | I69: Natural | J69: Premium | K69: 2800 | L69: 1500 | M69: 108000 | N69: =M69/'Input Costs'!$B$6 -> 1179.168 | O69: 25 | P69: 5 | Q69: =TODAY() -> 46062 | R69: Premium unbleached
A70: COLORED | B70: R-1P-17-VC | C70: Supplier A | D70: 1 | E70: 17 | F70: =D70*E70 -> 17 | G70: 1 | H70: No | I70: Colored | J70: Standard | K70: 2800 | L70: 1500 | M70: 112000 | N70: =M70/'Input Costs'!$B$6 -> 1222.8409 | O70: 28 | P70: 5 | Q70: =TODAY() -> 46062 | R70: Dyed tissue
B71: R-1P-18-VC | C71: Supplier A | D71: 1 | E71: 18 | F71: =D71*E71 -> 18 | G71: 1 | H71: No | I71: Colored | J71: Standard | K71: 2800 | L71: 1500 | M71: 110000 | N71: =M71/'Input Costs'!$B$6 -> 1201.0045 | O71: 28 | P71: 5 | Q71: =TODAY() -> 46062 | R71: Dyed napkin
B72: R-1P-20-VC | C72: Supplier A | D72: 1 | E72: 20 | F72: =D72*E72 -> 20 | G72: 1 | H72: No | I72: Colored | J72: Standard | K72: 2800 | L72: 1500 | M72: 107000 | N72: =M72/'Input Costs'!$B$6 -> 1168.2498 | O72: 28 | P72: 5 | Q72: =TODAY() -> 46062 | R72: Dyed tissue
B73: R-1P-22-VC | C73: Supplier A | D73: 1 | E73: 22 | F73: =D73*E73 -> 22 | G73: 1 | H73: No | I73: Colored | J73: Standard | K73: 2800 | L73: 1500 | M73: 105000 | N73: =M73/'Input Costs'!$B$6 -> 1146.4134 | O73: 28 | P73: 5 | Q73: =TODAY() -> 46062 | R73: Dyed tissue
B74: R-1P-18-VCP | C74: Supplier A | D74: 1 | E74: 18 | F74: =D74*E74 -> 18 | G74: 1 | H74: No | I74: Colored | J74: Premium | K74: 2800 | L74: 1500 | M74: 120000 | N74: =M74/'Input Costs'!$B$6 -> 1310.1867 | O74: 28 | P74: 5 | Q74: =TODAY() -> 46062 | R74: Premium dyed
A75: SUPPLIER B (ALTERNATE) | B75: R-1P-15-V-B | C75: Supplier B | D75: 1 | E75: 15 | F75: =D75*E75 -> 15 | G75: 1 | H75: No | I75: White | J75: Standard | K75: 2700 | L75: 1400 | M75: 103000 | N75: =M75/'Input Costs'!$B$6 -> 1124.5769 | O75: 18 | P75: 3 | Q75: =TODAY() -> 46062 | R75: Supplier B virgin
B76: R-1P-17-V-B | C76: Supplier B | D76: 1 | E76: 17 | F76: =D76*E76 -> 17 | G76: 1 | H76: No | I76: White | J76: Standard | K76: 2700 | L76: 1400 | M76: 100000 | N76: =M76/'Input Costs'!$B$6 -> 1091.8223 | O76: 18 | P76: 3 | Q76: =TODAY() -> 46062 | R76: Supplier B virgin
B77: R-1P-18-V-B | C77: Supplier B | D77: 1 | E77: 18 | F77: =D77*E77 -> 18 | G77: 1 | H77: No | I77: White | J77: Standard | K77: 2700 | L77: 1400 | M77: 98000 | N77: =M77/'Input Costs'!$B$6 -> 1069.9858 | O77: 18 | P77: 3 | Q77: =TODAY() -> 46062 | R77: Supplier B virgin
B78: R-1P-20-V-B | C78: Supplier B | D78: 1 | E78: 20 | F78: =D78*E78 -> 20 | G78: 1 | H78: No | I78: White | J78: Standard | K78: 2700 | L78: 1400 | M78: 95000 | N78: =M78/'Input Costs'!$B$6 -> 1037.2311 | O78: 18 | P78: 3 | Q78: =TODAY() -> 46062 | R78: Supplier B virgin
B79: R-1P-22-V-B | C79: Supplier B | D79: 1 | E79: 22 | F79: =D79*E79 -> 22 | G79: 1 | H79: No | I79: White | J79: Standard | K79: 2700 | L79: 1400 | M79: 93000 | N79: =M79/'Input Costs'!$B$6 -> 1015.3947 | O79: 18 | P79: 3 | Q79: =TODAY() -> 46062 | R79: Supplier B virgin
B80: R-1P-17-VP-B | C80: Supplier B | D80: 1 | E80: 17 | F80: =D80*E80 -> 17 | G80: 1 | H80: No | I80: White | J80: Premium | K80: 2700 | L80: 1400 | M80: 113000 | N80: =M80/'Input Costs'!$B$6 -> 1233.7591 | O80: 21 | P80: 3 | Q80: =TODAY() -> 46062 | R80: Supplier B premium
B81: R-1P-18-VP-B | C81: Supplier B | D81: 1 | E81: 18 | F81: =D81*E81 -> 18 | G81: 1 | H81: No | I81: White | J81: Premium | K81: 2700 | L81: 1400 | M81: 111000 | N81: =M81/'Input Costs'!$B$6 -> 1211.9227 | O81: 21 | P81: 3 | Q81: =TODAY() -> 46062 | R81: Supplier B premium
B82: R-1P-17-M70-B | C82: Supplier B | D82: 1 | E82: 17 | F82: =D82*E82 -> 17 | G82: 0.7 | H82: No | I82: White | J82: Standard | K82: 2700 | L82: 1400 | M82: 86000 | N82: =M82/'Input Costs'!$B$6 -> 938.96714 | O82: 18 | P82: 3 | Q82: =TODAY() -> 46062 | R82: Supplier B mixed
B83: R-1P-18-M70-B | C83: Supplier B | D83: 1 | E83: 18 | F83: =D83*E83 -> 18 | G83: 0.7 | H83: No | I83: White | J83: Standard | K83: 2700 | L83: 1400 | M83: 84000 | N83: =M83/'Input Costs'!$B$6 -> 917.13069 | O83: 18 | P83: 3 | Q83: =TODAY() -> 46062 | R83: Supplier B mixed
B84: R-1P-22-VW-B | C84: Supplier B | D84: 1 | E84: 22 | F84: =D84*E84 -> 22 | G84: 1 | H84: Yes | I84: White | J84: Standard | K84: 2700 | L84: 1400 | M84: 108000 | N84: =M84/'Input Costs'!$B$6 -> 1179.168 | O84: 21 | P84: 3 | Q84: =TODAY() -> 46062 | R84: Supplier B wet str
A85: SUPPLIER C (IMPORT) | B85: R-1P-15-V-C | C85: Supplier C | D85: 1 | E85: 15 | F85: =D85*E85 -> 15 | G85: 1 | H85: No | I85: White | J85: Standard | K85: 2850 | L85: 1600 | M85: 108000 | N85: =M85/'Input Costs'!$B$6 -> 1179.168 | O85: 45 | P85: 10 | Q85: =TODAY() -> 46062 | R85: Import virgin
B86: R-1P-17-V-C | C86: Supplier C | D86: 1 | E86: 17 | F86: =D86*E86 -> 17 | G86: 1 | H86: No | I86: White | J86: Standard | K86: 2850 | L86: 1600 | M86: 105000 | N86: =M86/'Input Costs'!$B$6 -> 1146.4134 | O86: 45 | P86: 10 | Q86: =TODAY() -> 46062 | R86: Import virgin
B87: R-1P-18-V-C | C87: Supplier C | D87: 1 | E87: 18 | F87: =D87*E87 -> 18 | G87: 1 | H87: No | I87: White | J87: Standard | K87: 2850 | L87: 1600 | M87: 103000 | N87: =M87/'Input Costs'!$B$6 -> 1124.5769 | O87: 45 | P87: 10 | Q87: =TODAY() -> 46062 | R87: Import virgin
B88: R-1P-20-V-C | C88: Supplier C | D88: 1 | E88: 20 | F88: =D88*E88 -> 20 | G88: 1 | H88: No | I88: White | J88: Standard | K88: 2850 | L88: 1600 | M88: 100000 | N88: =M88/'Input Costs'!$B$6 -> 1091.8223 | O88: 45 | P88: 10 | Q88: =TODAY() -> 46062 | R88: Import virgin
B89: R-1P-22-V-C | C89: Supplier C | D89: 1 | E89: 22 | F89: =D89*E89 -> 22 | G89: 1 | H89: No | I89: White | J89: Standard | K89: 2850 | L89: 1600 | M89: 98000 | N89: =M89/'Input Costs'!$B$6 -> 1069.9858 | O89: 45 | P89: 10 | Q89: =TODAY() -> 46062 | R89: Import virgin
B90: R-1P-17-VP-C | C90: Supplier C | D90: 1 | E90: 17 | F90: =D90*E90 -> 17 | G90: 1 | H90: No | I90: White | J90: Premium | K90: 2850 | L90: 1600 | M90: 120000 | N90: =M90/'Input Costs'!$B$6 -> 1310.1867 | O90: 45 | P90: 10 | Q90: =TODAY() -> 46062 | R90: Import premium
B91: R-1P-18-VP-C | C91: Supplier C | D91: 1 | E91: 18 | F91: =D91*E91 -> 18 | G91: 1 | H91: No | I91: White | J91: Premium | K91: 2850 | L91: 1600 | M91: 118000 | N91: =M91/'Input Costs'!$B$6 -> 1288.3503 | O91: 45 | P91: 10 | Q91: =TODAY() -> 46062 | R91: Import premium
B92: R-1P-22-VW-C | C92: Supplier C | D92: 1 | E92: 22 | F92: =D92*E92 -> 22 | G92: 1 | H92: Yes | I92: White | J92: Standard | K92: 2850 | L92: 1600 | M92: 115000 | N92: =M92/'Input Costs'!$B$6 -> 1255.5956 | O92: 45 | P92: 10 | Q92: =TODAY() -> 46062 | R92: Import wet strength
B93: R-1P-17-VN-C | C93: Supplier C | D93: 1 | E93: 17 | F93: =D93*E93 -> 17 | G93: 1 | H93: No | I93: Natural | J93: Premium | K93: 2850 | L93: 1600 | M93: 115000 | N93: =M93/'Input Costs'!$B$6 -> 1255.5956 | O93: 45 | P93: 10 | Q93: =TODAY() -> 46062 | R93: Import natural prem
B94: R-1P-18-VN-C | C94: Supplier C | D94: 1 | E94: 18 | F94: =D94*E94 -> 18 | G94: 1 | H94: No | I94: Natural | J94: Premium | K94: 2850 | L94: 1600 | M94: 113000 | N94: =M94/'Input Costs'!$B$6 -> 1233.7591 | O94: 45 | P94: 10 | Q94: =TODAY() -> 46062 | R94: Import natural prem
A95: SPECIALTY GRADES | B95: R-1P-14-TAD | C95: Supplier C | D95: 1 | E95: 14 | F95: =D95*E95 -> 14 | G95: 1 | H95: No | I95: White | J95: Premium | K95: 2850 | L95: 1600 | M95: 145000 | N95: =M95/'Input Costs'!$B$6 -> 1583.1423 | O95: 60 | P95: 10 | Q95: =TODAY() -> 46062 | R95: TAD tissue
B96: R-1P-16-TAD | C96: Supplier C | D96: 1 | E96: 16 | F96: =D96*E96 -> 16 | G96: 1 | H96: No | I96: White | J96: Premium | K96: 2850 | L96: 1600 | M96: 140000 | N96: =M96/'Input Costs'!$B$6 -> 1528.5512 | O96: 60 | P96: 10 | Q96: =TODAY() -> 46062 | R96: TAD tissue
B97: R-1P-18-TAD | C97: Supplier C | D97: 1 | E97: 18 | F97: =D97*E97 -> 18 | G97: 1 | H97: No | I97: White | J97: Premium | K97: 2850 | L97: 1600 | M97: 135000 | N97: =M97/'Input Costs'!$B$6 -> 1473.96 | O97: 60 | P97: 10 | Q97: =TODAY() -> 46062 | R97: TAD tissue
B98: R-1P-17-BAM | C98: Supplier D | D98: 1 | E98: 17 | F98: =D98*E98 -> 17 | G98: 1 | H98: No | I98: Natural | J98: Standard | K98: 2600 | L98: 1400 | M98: 125000 | N98: =M98/'Input Costs'!$B$6 -> 1364.7778 | O98: 45 | P98: 5 | Q98: =TODAY() -> 46062 | R98: Bamboo fiber
B99: R-1P-18-BAM | C99: Supplier D | D99: 1 | E99: 18 | F99: =D99*E99 -> 18 | G99: 1 | H99: No | I99: Natural | J99: Standard | K99: 2600 | L99: 1400 | M99: 122000 | N99: =M99/'Input Costs'!$B$6 -> 1332.0231 | O99: 45 | P99: 5 | Q99: =TODAY() -> 46062 | R99: Bamboo fiber
B100: R-1P-17-FSC | C100: Supplier A | D100: 1 | E100: 17 | F100: =D100*E100 -> 17 | G100: 1 | H100: No | I100: White | J100: Standard | K100: 2800 | L100: 1500 | M100: 108000 | N100: =M100/'Input Costs'!$B$6 -> 1179.168 | O100: 25 | P100: 5 | Q100: =TODAY() -> 46062 | R100: FSC certified
B101: R-1P-18-FSC | C101: Supplier A | D101: 1 | E101: 18 | F101: =D101*E101 -> 18 | G101: 1 | H101: No | I101: White | J101: Standard | K101: 2800 | L101: 1500 | M101: 106000 | N101: =M101/'Input Costs'!$B$6 -> 1157.3316 | O101: 25 | P101: 5 | Q101: =TODAY() -> 46062 | R101: FSC certified
B102: R-1P-17-FD | C102: Supplier A | D102: 1 | E102: 17 | F102: =D102*E102 -> 17 | G102: 1 | H102: No | I102: White | J102: Standard | K102: 2800 | L102: 1500 | M102: 110000 | N102: =M102/'Input Costs'!$B$6 -> 1201.0045 | O102: 25 | P102: 5 | Q102: =TODAY() -> 46062 | R102: Food grade certified
B103: R-1P-18-FD | C103: Supplier A | D103: 1 | E103: 18 | F103: =D103*E103 -> 18 | G103: 1 | H103: No | I103: White | J103: Standard | K103: 2800 | L103: 1500 | M103: 108000 | N103: =M103/'Input Costs'!$B$6 -> 1179.168 | O103: 25 | P103: 5 | Q103: =TODAY() -> 46062 | R103: Food grade certified
A104: 2-PLY VIRGIN WHITE SOFTNESS | B104: R-2P-13-V | C104: Supplier A | D104: 2 | E104: 13 | F104: =D104*E104 -> 26 | G104: 1 | H104: No | I104: White | J104: Standard | K104: 2800 | L104: 1500 | M104: 118000 | N104: =M104/'Input Costs'!$B$6 -> 1288.3503 | O104: 25 | P104: 5 | Q104: =TODAY() -> 46062 | R104: Ultra light 2-ply
B105: R-2P-14-V | C105: Supplier A | D105: 2 | E105: 14 | F105: =D105*E105 -> 28 | G105: 1 | H105: No | I105: White | J105: Standard | K105: 2800 | L105: 1500 | M105: 114000 | N105: =M105/'Input Costs'!$B$6 -> 1244.6774 | O105: 25 | P105: 5 | Q105: =TODAY() -> 46062 | R105: Light facial 2-ply
B106: R-2P-15-V | C106: Supplier A | D106: 2 | E106: 15 | F106: =D106*E106 -> 30 | G106: 1 | H106: No | I106: White | J106: Standard | K106: 2800 | L106: 1500 | M106: 111000 | N106: =M106/'Input Costs'!$B$6 -> 1211.9227 | O106: 25 | P106: 5 | Q106: =TODAY() -> 46062 | R106: Standard facial 2-ply
...

Sheet Input Products
A1: Product_Description | B1: Product_Code | C1: Product_Name | D1: Category | E1: Ply | F1: GSM_Per_Ply | G1: Sheet_Length_mm | H1: Sheet_Width_mm | I1: Sheet_Area_m2 | J1: Sheets_Per_Unit | K1: Core_Weight_g | L1: Core_ID_mm | M1: Roll_Dia_mm | N1: Wet_Strength | O1: Color | P1: Emboss | Q1: Print | R1: Wrap_Type | S1: Units_Per_Carton | T1: Cartons_Per_Pallet | U1: Pallets_Per_40HC | V1: Matched_Reel_Code | W1: Certification
A2: TOILET ROLLS
A3: 2-PLY STANDARD VIRGIN | B3: TT-2P-100-S | C3: Toilet Roll 2P 100Sht Std | D3: TT | E3: 2 | F3: 17 | G3: 100 | H3: 114 | I3: =G3*H3/1000000 -> 0.0114 | J3: 100 | K3: 6 | L3: 40 | M3: 85 | N3: No | O3: White | P3: Standard | Q3: No | R3: Printed | S3: 96 | T3: 72 | U3: 20 | V3: R-1P-17-V | W3: None
B4: TT-2P-150-S | C4: Toilet Roll 2P 150Sht Std | D4: TT | E4: 2 | F4: 17 | G4: 100 | H4: 114 | I4: =G4*H4/1000000 -> 0.0114 | J4: 150 | K4: 7 | L4: 40 | M4: 95 | N4: No | O4: White | P4: Standard | Q4: No | R4: Printed | S4: 64 | T4: 64 | U4: 20 | V4: R-1P-17-V | W4: None
B5: TT-2P-180-S | C5: Toilet Roll 2P 180Sht Std | D5: TT | E5: 2 | F5: 17 | G5: 100 | H5: 114 | I5: =G5*H5/1000000 -> 0.0114 | J5: 180 | K5: 8 | L5: 40 | M5: 100 | N5: No | O5: White | P5: Standard | Q5: No | R5: Printed | S5: 56 | T5: 60 | U5: 20 | V5: R-1P-17-V | W5: None
B6: TT-2P-200-S | C6: Toilet Roll 2P 200Sht Std | D6: TT | E6: 2 | F6: 17 | G6: 100 | H6: 114 | I6: =G6*H6/1000000 -> 0.0114 | J6: 200 | K6: 8 | L6: 40 | M6: 105 | N6: No | O6: White | P6: Standard | Q6: No | R6: Printed | S6: 48 | T6: 60 | U6: 20 | V6: R-1P-17-V | W6: None
B7: TT-2P-220-S | C7: Toilet Roll 2P 220Sht Std | D7: TT | E7: 2 | F7: 17 | G7: 100 | H7: 114 | I7: =G7*H7/1000000 -> 0.0114 | J7: 220 | K7: 9 | L7: 40 | M7: 108 | N7: No | O7: White | P7: Standard | Q7: No | R7: Printed | S7: 48 | T7: 56 | U7: 20 | V7: R-1P-17-V | W7: None
B8: TT-2P-250-S | C8: Toilet Roll 2P 250Sht Std | D8: TT | E8: 2 | F8: 17 | G8: 100 | H8: 114 | I8: =G8*H8/1000000 -> 0.0114 | J8: 250 | K8: 9 | L8: 40 | M8: 112 | N8: No | O8: White | P8: Standard | Q8: No | R8: Printed | S8: 40 | T8: 56 | U8: 20 | V8: R-1P-17-V | W8: None
B9: TT-2P-300-S | C9: Toilet Roll 2P 300Sht Std | D9: TT | E9: 2 | F9: 17 | G9: 100 | H9: 114 | I9: =G9*H9/1000000 -> 0.0114 | J9: 300 | K9: 10 | L9: 40 | M9: 120 | N9: No | O9: White | P9: Standard | Q9: No | R9: Printed | S9: 36 | T9: 56 | U9: 20 | V9: R-1P-17-V | W9: None
B10: TT-2P-350-S | C10: Toilet Roll 2P 350Sht Std | D10: TT | E10: 2 | F10: 17 | G10: 100 | H10: 114 | I10: =G10*H10/1000000 -> 0.0114 | J10: 350 | K10: 11 | L10: 40 | M10: 128 | N10: No | O10: White | P10: Standard | Q10: No | R10: Printed | S10: 32 | T10: 52 | U10: 20 | V10: R-1P-17-V | W10: None
B11: TT-2P-400-S | C11: Toilet Roll 2P 400Sht Std | D11: TT | E11: 2 | F11: 17 | G11: 100 | H11: 114 | I11: =G11*H11/1000000 -> 0.0114 | J11: 400 | K11: 12 | L11: 40 | M11: 135 | N11: No | O11: White | P11: Standard | Q11: No | R11: Printed | S11: 28 | T11: 48 | U11: 20 | V11: R-1P-17-V | W11: None
B12: TT-2P-500-S | C12: Toilet Roll 2P 500Sht Std | D12: TT | E12: 2 | F12: 17 | G12: 100 | H12: 114 | I12: =G12*H12/1000000 -> 0.0114 | J12: 500 | K12: 12 | L12: 40 | M12: 145 | N12: No | O12: White | P12: Standard | Q12: No | R12: Printed | S12: 24 | T12: 48 | U12: 20 | V12: R-1P-17-V | W12: None
B13: TT-2P-600-S | C13: Toilet Roll 2P 600Sht Std | D13: TT | E13: 2 | F13: 17 | G13: 100 | H13: 114 | I13: =G13*H13/1000000 -> 0.0114 | J13: 600 | K13: 14 | L13: 40 | M13: 155 | N13: No | O13: White | P13: Standard | Q13: No | R13: Printed | S13: 20 | T13: 44 | U13: 20 | V13: R-1P-17-V | W13: None
B14: TT-2P-800-S | C14: Toilet Roll 2P 800Sht Std | D14: TT | E14: 2 | F14: 17 | G14: 100 | H14: 114 | I14: =G14*H14/1000000 -> 0.0114 | J14: 800 | K14: 16 | L14: 40 | M14: 175 | N14: No | O14: White | P14: Standard | Q14: No | R14: Printed | S14: 16 | T14: 40 | U14: 20 | V14: R-1P-17-V | W14: None
B15: TT-2P-1000-S | C15: Toilet Roll 2P 1000Sht Std | D15: TT | E15: 2 | F15: 17 | G15: 100 | H15: 114 | I15: =G15*H15/1000000 -> 0.0114 | J15: 1000 | K15: 18 | L15: 40 | M15: 195 | N15: No | O15: White | P15: Standard | Q15: No | R15: Printed | S15: 12 | T15: 36 | U15: 20 | V15: R-1P-17-V | W15: None
A16: 2-PLY DEEP EMBOSS VIRGIN | B16: TT-2P-150-D | C16: Toilet Roll 2P 150Sht Deep | D16: TT | E16: 2 | F16: 17 | G16: 100 | H16: 114 | I16: =G16*H16/1000000 -> 0.0114 | J16: 150 | K16: 7 | L16: 40 | M16: 98 | N16: No | O16: White | P16: Deep | Q16: No | R16: Printed | S16: 64 | T16: 64 | U16: 20 | V16: R-1P-17-V | W16: None
B17: TT-2P-200-D | C17: Toilet Roll 2P 200Sht Deep | D17: TT | E17: 2 | F17: 17 | G17: 100 | H17: 114 | I17: =G17*H17/1000000 -> 0.0114 | J17: 200 | K17: 8 | L17: 40 | M17: 108 | N17: No | O17: White | P17: Deep | Q17: No | R17: Printed | S17: 48 | T17: 60 | U17: 20 | V17: R-1P-17-V | W17: None
B18: TT-2P-250-D | C18: Toilet Roll 2P 250Sht Deep | D18: TT | E18: 2 | F18: 17 | G18: 100 | H18: 114 | I18: =G18*H18/1000000 -> 0.0114 | J18: 250 | K18: 9 | L18: 40 | M18: 115 | N18: No | O18: White | P18: Deep | Q18: No | R18: Printed | S18: 40 | T18: 56 | U18: 20 | V18: R-1P-17-V | W18: None
B19: TT-2P-300-D | C19: Toilet Roll 2P 300Sht Deep | D19: TT | E19: 2 | F19: 17 | G19: 100 | H19: 114 | I19: =G19*H19/1000000 -> 0.0114 | J19: 300 | K19: 10 | L19: 40 | M19: 125 | N19: No | O19: White | P19: Deep | Q19: No | R19: Printed | S19: 36 | T19: 52 | U19: 20 | V19: R-1P-17-V | W19: None
B20: TT-2P-400-D | C20: Toilet Roll 2P 400Sht Deep | D20: TT | E20: 2 | F20: 17 | G20: 100 | H20: 114 | I20: =G20*H20/1000000 -> 0.0114 | J20: 400 | K20: 12 | L20: 40 | M20: 140 | N20: No | O20: White | P20: Deep | Q20: No | R20: Printed | S20: 28 | T20: 48 | U20: 20 | V20: R-1P-17-V | W20: None
B21: TT-2P-500-D | C21: Toilet Roll 2P 500Sht Deep | D21: TT | E21: 2 | F21: 17 | G21: 100 | H21: 114 | I21: =G21*H21/1000000 -> 0.0114 | J21: 500 | K21: 12 | L21: 40 | M21: 150 | N21: No | O21: White | P21: Deep | Q21: No | R21: Printed | S21: 24 | T21: 44 | U21: 20 | V21: R-1P-17-V | W21: None
A22: 2-PLY PREMIUM SOFTNESS | B22: TT-2P-150-P | C22: Toilet Roll 2P 150Sht Prem | D22: TT | E22: 2 | F22: 17 | G22: 100 | H22: 114 | I22: =G22*H22/1000000 -> 0.0114 | J22: 150 | K22: 7 | L22: 40 | M22: 98 | N22: No | O22: White | P22: Deep | Q22: No | R22: Printed | S22: 64 | T22: 60 | U22: 20 | V22: R-1P-17-VP | W22: None
B23: TT-2P-200-P | C23: Toilet Roll 2P 200Sht Prem | D23: TT | E23: 2 | F23: 17 | G23: 100 | H23: 114 | I23: =G23*H23/1000000 -> 0.0114 | J23: 200 | K23: 8 | L23: 40 | M23: 108 | N23: No | O23: White | P23: Deep | Q23: No | R23: Printed | S23: 48 | T23: 56 | U23: 20 | V23: R-1P-17-VP | W23: None
B24: TT-2P-250-P | C24: Toilet Roll 2P 250Sht Prem | D24: TT | E24: 2 | F24: 17 | G24: 100 | H24: 114 | I24: =G24*H24/1000000 -> 0.0114 | J24: 250 | K24: 9 | L24: 40 | M24: 115 | N24: No | O24: White | P24: Deep | Q24: No | R24: Printed | S24: 40 | T24: 52 | U24: 20 | V24: R-1P-17-VP | W24: None
B25: TT-2P-300-P | C25: Toilet Roll 2P 300Sht Prem | D25: TT | E25: 2 | F25: 17 | G25: 100 | H25: 114 | I25: =G25*H25/1000000 -> 0.0114 | J25: 300 | K25: 10 | L25: 40 | M25: 125 | N25: No | O25: White | P25: Deep | Q25: No | R25: Printed | S25: 36 | T25: 48 | U25: 20 | V25: R-1P-17-VP | W25: None
B26: TT-2P-400-P | C26: Toilet Roll 2P 400Sht Prem | D26: TT | E26: 2 | F26: 17 | G26: 100 | H26: 114 | I26: =G26*H26/1000000 -> 0.0114 | J26: 400 | K26: 12 | L26: 40 | M26: 140 | N26: No | O26: White | P26: Deep | Q26: No | R26: Printed | S26: 28 | T26: 44 | U26: 20 | V26: R-1P-17-VP | W26: None
B27: TT-2P-500-P | C27: Toilet Roll 2P 500Sht Prem | D27: TT | E27: 2 | F27: 17 | G27: 100 | H27: 114 | I27: =G27*H27/1000000 -> 0.0114 | J27: 500 | K27: 12 | L27: 40 | M27: 150 | N27: No | O27: White | P27: Deep | Q27: No | R27: Printed | S27: 24 | T27: 40 | U27: 20 | V27: R-1P-17-VP | W27: None
A28: 2-PLY ECONOMY (MIXED FIBER) | B28: TT-2P-150-E | C28: Toilet Roll 2P 150Sht Eco | D28: TT | E28: 2 | F28: 17 | G28: 100 | H28: 114 | I28: =G28*H28/1000000 -> 0.0114 | J28: 150 | K28: 7 | L28: 40 | M28: 95 | N28: No | O28: White | P28: Light | Q28: No | R28: Plain | S28: 64 | T28: 64 | U28: 20 | V28: R-1P-17-M70 | W28: None
B29: TT-2P-200-E | C29: Toilet Roll 2P 200Sht Eco | D29: TT | E29: 2 | F29: 17 | G29: 100 | H29: 114 | I29: =G29*H29/1000000 -> 0.0114 | J29: 200 | K29: 8 | L29: 40 | M29: 105 | N29: No | O29: White | P29: Light | Q29: No | R29: Plain | S29: 48 | T29: 60 | U29: 20 | V29: R-1P-17-M70 | W29: None
B30: TT-2P-250-E | C30: Toilet Roll 2P 250Sht Eco | D30: TT | E30: 2 | F30: 17 | G30: 100 | H30: 114 | I30: =G30*H30/1000000 -> 0.0114 | J30: 250 | K30: 9 | L30: 40 | M30: 112 | N30: No | O30: White | P30: Light | Q30: No | R30: Plain | S30: 40 | T30: 56 | U30: 20 | V30: R-1P-17-M70 | W30: None
B31: TT-2P-300-E | C31: Toilet Roll 2P 300Sht Eco | D31: TT | E31: 2 | F31: 17 | G31: 100 | H31: 114 | I31: =G31*H31/1000000 -> 0.0114 | J31: 300 | K31: 10 | L31: 40 | M31: 120 | N31: No | O31: White | P31: Light | Q31: No | R31: Plain | S31: 36 | T31: 56 | U31: 20 | V31: R-1P-17-M70 | W31: None
B32: TT-2P-400-E | C32: Toilet Roll 2P 400Sht Eco | D32: TT | E32: 2 | F32: 17 | G32: 100 | H32: 114 | I32: =G32*H32/1000000 -> 0.0114 | J32: 400 | K32: 12 | L32: 40 | M32: 135 | N32: No | O32: White | P32: Light | Q32: No | R32: Plain | S32: 28 | T32: 48 | U32: 20 | V32: R-1P-17-M70 | W32: None
B33: TT-2P-500-E | C33: Toilet Roll 2P 500Sht Eco | D33: TT | E33: 2 | F33: 17 | G33: 100 | H33: 114 | I33: =G33*H33/1000000 -> 0.0114 | J33: 500 | K33: 12 | L33: 40 | M33: 145 | N33: No | O33: White | P33: Light | Q33: No | R33: Plain | S33: 24 | T33: 48 | U33: 20 | V33: R-1P-17-M70 | W33: None
B34: TT-2P-600-E | C34: Toilet Roll 2P 600Sht Eco | D34: TT | E34: 2 | F34: 17 | G34: 100 | H34: 114 | I34: =G34*H34/1000000 -> 0.0114 | J34: 600 | K34: 14 | L34: 40 | M34: 155 | N34: No | O34: White | P34: Light | Q34: No | R34: Plain | S34: 20 | T34: 44 | U34: 20 | V34: R-1P-17-M70 | W34: None
B35: TT-2P-200-E50 | C35: Toilet Roll 2P 200Sht Eco50 | D35: TT | E35: 2 | F35: 17 | G35: 100 | H35: 114 | I35: =G35*H35/1000000 -> 0.0114 | J35: 200 | K35: 8 | L35: 40 | M35: 105 | N35: No | O35: White | P35: Light | Q35: No | R35: Plain | S35: 48 | T35: 60 | U35: 20 | V35: R-1P-17-M50 | W35: None
B36: TT-2P-300-E50 | C36: Toilet Roll 2P 300Sht Eco50 | D36: TT | E36: 2 | F36: 17 | G36: 100 | H36: 114 | I36: =G36*H36/1000000 -> 0.0114 | J36: 300 | K36: 10 | L36: 40 | M36: 120 | N36: No | O36: White | P36: Light | Q36: No | R36: Plain | S36: 36 | T36: 56 | U36: 20 | V36: R-1P-17-M50 | W36: None
A37: 2-PLY RECYCLED | B37: TT-2P-200-R | C37: Toilet Roll 2P 200Sht Recy | D37: TT | E37: 2 | F37: 17 | G37: 100 | H37: 114 | I37: =G37*H37/1000000 -> 0.0114 | J37: 200 | K37: 8 | L37: 40 | M37: 105 | N37: No | O37: White | P37: Light | Q37: No | R37: Plain | S37: 48 | T37: 60 | U37: 20 | V37: R-1P-17-R | W37: None
B38: TT-2P-300-R | C38: Toilet Roll 2P 300Sht Recy | D38: TT | E38: 2 | F38: 17 | G38: 100 | H38: 114 | I38: =G38*H38/1000000 -> 0.0114 | J38: 300 | K38: 10 | L38: 40 | M38: 120 | N38: No | O38: White | P38: Light | Q38: No | R38: Plain | S38: 36 | T38: 56 | U38: 20 | V38: R-1P-17-R | W38: None
B39: TT-2P-400-R | C39: Toilet Roll 2P 400Sht Recy | D39: TT | E39: 2 | F39: 17 | G39: 100 | H39: 114 | I39: =G39*H39/1000000 -> 0.0114 | J39: 400 | K39: 12 | L39: 40 | M39: 135 | N39: No | O39: White | P39: Light | Q39: No | R39: Plain | S39: 28 | T39: 48 | U39: 20 | V39: R-1P-17-R | W39: None
B40: TT-2P-500-R | C40: Toilet Roll 2P 500Sht Recy | D40: TT | E40: 2 | F40: 17 | G40: 100 | H40: 114 | I40: =G40*H40/1000000 -> 0.0114 | J40: 500 | K40: 12 | L40: 40 | M40: 145 | N40: No | O40: White | P40: Light | Q40: No | R40: Plain | S40: 24 | T40: 48 | U40: 20 | V40: R-1P-17-R | W40: None
A41: 2-PLY NATURAL/ UNBLEACHED | B41: TT-2P-150-N | C41: Toilet Roll 2P 150Sht Nat | D41: TT | E41: 2 | F41: 17 | G41: 100 | H41: 114 | I41: =G41*H41/1000000 -> 0.0114 | J41: 150 | K41: 7 | L41: 40 | M41: 95 | N41: No | O41: Natural | P41: Standard | Q41: No | R41: Paper | S41: 64 | T41: 64 | U41: 20 | V41: R-1P-17-VN | W41: FSC
B42: TT-2P-200-N | C42: Toilet Roll 2P 200Sht Nat | D42: TT | E42: 2 | F42: 17 | G42: 100 | H42: 114 | I42: =G42*H42/1000000 -> 0.0114 | J42: 200 | K42: 8 | L42: 40 | M42: 105 | N42: No | O42: Natural | P42: Standard | Q42: No | R42: Paper | S42: 48 | T42: 60 | U42: 20 | V42: R-1P-17-VN | W42: FSC
B43: TT-2P-250-N | C43: Toilet Roll 2P 250Sht Nat | D43: TT | E43: 2 | F43: 17 | G43: 100 | H43: 114 | I43: =G43*H43/1000000 -> 0.0114 | J43: 250 | K43: 9 | L43: 40 | M43: 112 | N43: No | O43: Natural | P43: Standard | Q43: No | R43: Paper | S43: 40 | T43: 56 | U43: 20 | V43: R-1P-17-VN | W43: FSC
B44: TT-2P-300-N | C44: Toilet Roll 2P 300Sht Nat | D44: TT | E44: 2 | F44: 17 | G44: 100 | H44: 114 | I44: =G44*H44/1000000 -> 0.0114 | J44: 300 | K44: 10 | L44: 40 | M44: 120 | N44: No | O44: Natural | P44: Standard | Q44: No | R44: Paper | S44: 36 | T44: 56 | U44: 20 | V44: R-1P-17-VN | W44: FSC
B45: TT-2P-400-N | C45: Toilet Roll 2P 400Sht Nat | D45: TT | E45: 2 | F45: 17 | G45: 100 | H45: 114 | I45: =G45*H45/1000000 -> 0.0114 | J45: 400 | K45: 12 | L45: 40 | M45: 135 | N45: No | O45: Natural | P45: Standard | Q45: No | R45: Paper | S45: 28 | T45: 48 | U45: 20 | V45: R-1P-17-VN | W45: FSC
B46: TT-2P-200-NP | C46: Toilet Roll 2P 200Sht NatPr | D46: TT | E46: 2 | F46: 17 | G46: 100 | H46: 114 | I46: =G46*H46/1000000 -> 0.0114 | J46: 200 | K46: 8 | L46: 40 | M46: 108 | N46: No | O46: Natural | P46: Deep | Q46: No | R46: Paper | S46: 48 | T46: 56 | U46: 20 | V46: R-1P-17-VNP | W46: FSC
B47: TT-2P-300-NP | C47: Toilet Roll 2P 300Sht NatPr | D47: TT | E47: 2 | F47: 17 | G47: 100 | H47: 114 | I47: =G47*H47/1000000 -> 0.0114 | J47: 300 | K47: 10 | L47: 40 | M47: 125 | N47: No | O47: Natural | P47: Deep | Q47: No | R47: Paper | S47: 36 | T47: 52 | U47: 20 | V47: R-1P-17-VNP | W47: FSC
A48: 2-PLY FSC CERTIFIED | B48: TT-2P-200-FSC | C48: Toilet Roll 2P 200Sht FSC | D48: TT | E48: 2 | F48: 17 | G48: 100 | H48: 114 | I48: =G48*H48/1000000 -> 0.0114 | J48: 200 | K48: 8 | L48: 40 | M48: 105 | N48: No | O48: White | P48: Standard | Q48: No | R48: Printed | S48: 48 | T48: 60 | U48: 20 | V48: R-1P-17-FSC | W48: FSC
B49: TT-2P-300-FSC | C49: Toilet Roll 2P 300Sht FSC | D49: TT | E49: 2 | F49: 17 | G49: 100 | H49: 114 | I49: =G49*H49/1000000 -> 0.0114 | J49: 300 | K49: 10 | L49: 40 | M49: 120 | N49: No | O49: White | P49: Standard | Q49: No | R49: Printed | S49: 36 | T49: 56 | U49: 20 | V49: R-1P-17-FSC | W49: FSC
B50: TT-2P-400-FSC | C50: Toilet Roll 2P 400Sht FSC | D50: TT | E50: 2 | F50: 17 | G50: 100 | H50: 114 | I50: =G50*H50/1000000 -> 0.0114 | J50: 400 | K50: 12 | L50: 40 | M50: 135 | N50: No | O50: White | P50: Standard | Q50: No | R50: Printed | S50: 28 | T50: 48 | U50: 20 | V50: R-1P-17-FSC | W50: FSC
B51: TT-2P-500-FSC | C51: Toilet Roll 2P 500Sht FSC | D51: TT | E51: 2 | F51: 17 | G51: 100 | H51: 114 | I51: =G51*H51/1000000 -> 0.0114 | J51: 500 | K51: 12 | L51: 40 | M51: 145 | N51: No | O51: White | P51: Standard | Q51: No | R51: Printed | S51: 24 | T51: 48 | U51: 20 | V51: R-1P-17-FSC | W51: FSC
A52: 3-PLY STANDARD VIRGIN | B52: TT-3P-100-S | C52: Toilet Roll 3P 100Sht Std | D52: TT | E52: 3 | F52: 15 | G52: 100 | H52: 114 | I52: =G52*H52/1000000 -> 0.0114 | J52: 100 | K52: 6 | L52: 40 | M52: 90 | N52: No | O52: White | P52: Standard | Q52: No | R52: Printed | S52: 80 | T52: 64 | U52: 20 | V52: R-1P-15-V | W52: None
B53: TT-3P-120-S | C53: Toilet Roll 3P 120Sht Std | D53: TT | E53: 3 | F53: 15 | G53: 100 | H53: 114 | I53: =G53*H53/1000000 -> 0.0114 | J53: 120 | K53: 7 | L53: 40 | M53: 95 | N53: No | O53: White | P53: Standard | Q53: No | R53: Printed | S53: 72 | T53: 60 | U53: 20 | V53: R-1P-15-V | W53: None
B54: TT-3P-150-S | C54: Toilet Roll 3P 150Sht Std | D54: TT | E54: 3 | F54: 15 | G54: 100 | H54: 114 | I54: =G54*H54/1000000 -> 0.0114 | J54: 150 | K54: 8 | L54: 40 | M54: 102 | N54: No | O54: White | P54: Standard | Q54: No | R54: Printed | S54: 56 | T54: 56 | U54: 20 | V54: R-1P-15-V | W54: None
B55: TT-3P-180-S | C55: Toilet Roll 3P 180Sht Std | D55: TT | E55: 3 | F55: 15 | G55: 100 | H55: 114 | I55: =G55*H55/1000000 -> 0.0114 | J55: 180 | K55: 9 | L55: 40 | M55: 108 | N55: No | O55: White | P55: Standard | Q55: No | R55: Printed | S55: 48 | T55: 52 | U55: 20 | V55: R-1P-15-V | W55: None
B56: TT-3P-200-S | C56: Toilet Roll 3P 200Sht Std | D56: TT | E56: 3 | F56: 15 | G56: 100 | H56: 114 | I56: =G56*H56/1000000 -> 0.0114 | J56: 200 | K56: 9 | L56: 40 | M56: 115 | N56: No | O56: White | P56: Standard | Q56: No | R56: Printed | S56: 40 | T56: 48 | U56: 20 | V56: R-1P-15-V | W56: None
B57: TT-3P-250-S | C57: Toilet Roll 3P 250Sht Std | D57: TT | E57: 3 | F57: 15 | G57: 100 | H57: 114 | I57: =G57*H57/1000000 -> 0.0114 | J57: 250 | K57: 10 | L57: 40 | M57: 125 | N57: No | O57: White | P57: Standard | Q57: No | R57: Printed | S57: 32 | T57: 44 | U57: 20 | V57: R-1P-15-V | W57: None
B58: TT-3P-300-S | C58: Toilet Roll 3P 300Sht Std | D58: TT | E58: 3 | F58: 15 | G58: 100 | H58: 114 | I58: =G58*H58/1000000 -> 0.0114 | J58: 300 | K58: 11 | L58: 40 | M58: 135 | N58: No | O58: White | P58: Standard | Q58: No | R58: Printed | S58: 28 | T58: 40 | U58: 20 | V58: R-1P-15-V | W58: None
B59: TT-3P-400-S | C59: Toilet Roll 3P 400Sht Std | D59: TT | E59: 3 | F59: 15 | G59: 100 | H59: 114 | I59: =G59*H59/1000000 -> 0.0114 | J59: 400 | K59: 12 | L59: 40 | M59: 150 | N59: No | O59: White | P59: Standard | Q59: No | R59: Printed | S59: 24 | T59: 36 | U59: 20 | V59: R-1P-15-V | W59: None
A60: 3-PLY PREMIUM SOFTNESS | B60: TT-3P-120-P | C60: Toilet Roll 3P 120Sht Prem | D60: TT | E60: 3 | F60: 15 | G60: 100 | H60: 114 | I60: =G60*H60/1000000 -> 0.0114 | J60: 120 | K60: 7 | L60: 40 | M60: 98 | N60: No | O60: White | P60: Deep | Q60: No | R60: Printed | S60: 72 | T60: 56 | U60: 20 | V60: R-1P-15-VP | W60: None
B61: TT-3P-150-P | C61: Toilet Roll 3P 150Sht Prem | D61: TT | E61: 3 | F61: 15 | G61: 100 | H61: 114 | I61: =G61*H61/1000000 -> 0.0114 | J61: 150 | K61: 8 | L61: 40 | M61: 105 | N61: No | O61: White | P61: Deep | Q61: No | R61: Printed | S61: 56 | T61: 52 | U61: 20 | V61: R-1P-15-VP | W61: None
B62: TT-3P-180-P | C62: Toilet Roll 3P 180Sht Prem | D62: TT | E62: 3 | F62: 15 | G62: 100 | H62: 114 | I62: =G62*H62/1000000 -> 0.0114 | J62: 180 | K62: 9 | L62: 40 | M62: 112 | N62: No | O62: White | P62: Deep | Q62: No | R62: Printed | S62: 48 | T62: 48 | U62: 20 | V62: R-1P-15-VP | W62: None
B63: TT-3P-200-P | C63: Toilet Roll 3P 200Sht Prem | D63: TT | E63: 3 | F63: 15 | G63: 100 | H63: 114 | I63: =G63*H63/1000000 -> 0.0114 | J63: 200 | K63: 9 | L63: 40 | M63: 118 | N63: No | O63: White | P63: Deep | Q63: No | R63: Printed | S63: 40 | T63: 44 | U63: 20 | V63: R-1P-15-VP | W63: None
B64: TT-3P-250-P | C64: Toilet Roll 3P 250Sht Prem | D64: TT | E64: 3 | F64: 15 | G64: 100 | H64: 114 | I64: =G64*H64/1000000 -> 0.0114 | J64: 250 | K64: 10 | L64: 40 | M64: 128 | N64: No | O64: White | P64: Deep | Q64: No | R64: Printed | S64: 32 | T64: 40 | U64: 20 | V64: R-1P-15-VP | W64: None
B65: TT-3P-300-P | C65: Toilet Roll 3P 300Sht Prem | D65: TT | E65: 3 | F65: 15 | G65: 100 | H65: 114 | I65: =G65*H65/1000000 -> 0.0114 | J65: 300 | K65: 11 | L65: 40 | M65: 138 | N65: No | O65: White | P65: Deep | Q65: No | R65: Printed | S65: 28 | T65: 36 | U65: 20 | V65: R-1P-15-VP | W65: None
A66: 3-PLY ULTRA PREMIUM | B66: TT-3P-120-UP | C66: Toilet Roll 3P 120Sht UltPr | D66: TT | E66: 3 | F66: 14 | G66: 100 | H66: 114 | I66: =G66*H66/1000000 -> 0.0114 | J66: 120 | K66: 7 | L66: 40 | M66: 95 | N66: No | O66: White | P66: Deep | Q66: No | R66: Printed | S66: 72 | T66: 56 | U66: 20 | V66: R-3P-14-VUP | W66: None
B67: TT-3P-150-UP | C67: Toilet Roll 3P 150Sht UltPr | D67: TT | E67: 3 | F67: 14 | G67: 100 | H67: 114 | I67: =G67*H67/1000000 -> 0.0114 | J67: 150 | K67: 8 | L67: 40 | M67: 102 | N67: No | O67: White | P67: Deep | Q67: No | R67: Printed | S67: 56 | T67: 52 | U67: 20 | V67: R-3P-14-VUP | W67: None
B68: TT-3P-180-UP | C68: Toilet Roll 3P 180Sht UltPr | D68: TT | E68: 3 | F68: 14 | G68: 100 | H68: 114 | I68: =G68*H68/1000000 -> 0.0114 | J68: 180 | K68: 9 | L68: 40 | M68: 108 | N68: No | O68: White | P68: Deep | Q68: No | R68: Printed | S68: 48 | T68: 48 | U68: 20 | V68: R-3P-14-VUP | W68: None
B69: TT-3P-200-UP | C69: Toilet Roll 3P 200Sht UltPr | D69: TT | E69: 3 | F69: 14 | G69: 100 | H69: 114 | I69: =G69*H69/1000000 -> 0.0114 | J69: 200 | K69: 9 | L69: 40 | M69: 115 | N69: No | O69: White | P69: Deep | Q69: No | R69: Printed | S69: 40 | T69: 44 | U69: 20 | V69: R-3P-14-VUP | W69: None
B70: TT-3P-250-UP | C70: Toilet Roll 3P 250Sht UltPr | D70: TT | E70: 3 | F70: 14 | G70: 100 | H70: 114 | I70: =G70*H70/1000000 -> 0.0114 | J70: 250 | K70: 10 | L70: 40 | M70: 125 | N70: No | O70: White | P70: Deep | Q70: No | R70: Printed | S70: 32 | T70: 40 | U70: 20 | V70: R-3P-14-VUP | W70: None
A71: 3-PLY LOTION/ ALOE VERA | B71: TT-3P-150-L | C71: Toilet Roll 3P 150Sht Lotion | D71: TT | E71: 3 | F71: 15 | G71: 100 | H71: 114 | I71: =G71*H71/1000000 -> 0.0114 | J71: 150 | K71: 8 | L71: 40 | M71: 105 | N71: No | O71: White | P71: Deep | Q71: No | R71: Printed | S71: 56 | T71: 52 | U71: 20 | V71: R-3P-15-VL | W71: None
B72: TT-3P-200-L | C72: Toilet Roll 3P 200Sht Lotion | D72: TT | E72: 3 | F72: 15 | G72: 100 | H72: 114 | I72: =G72*H72/1000000 -> 0.0114 | J72: 200 | K72: 9 | L72: 40 | M72: 118 | N72: No | O72: White | P72: Deep | Q72: No | R72: Printed | S72: 40 | T72: 44 | U72: 20 | V72: R-3P-15-VL | W72: None
B73: TT-3P-150-A | C73: Toilet Roll 3P 150Sht Aloe | D73: TT | E73: 3 | F73: 15 | G73: 100 | H73: 114 | I73: =G73*H73/1000000 -> 0.0114 | J73: 150 | K73: 8 | L73: 40 | M73: 105 | N73: No | O73: White | P73: Deep | Q73: No | R73: Printed | S73: 56 | T73: 52 | U73: 20 | V73: R-3P-15-VLA | W73: None
B74: TT-3P-200-A | C74: Toilet Roll 3P 200Sht Aloe | D74: TT | E74: 3 | F74: 15 | G74: 100 | H74: 114 | I74: =G74*H74/1000000 -> 0.0114 | J74: 200 | K74: 9 | L74: 40 | M74: 118 | N74: No | O74: White | P74: Deep | Q74: No | R74: Printed | S74: 40 | T74: 44 | U74: 20 | V74: R-3P-15-VLA | W74: None
A75: 3-PLY NATURAL | B75: TT-3P-150-N | C75: Toilet Roll 3P 150Sht Nat | D75: TT | E75: 3 | F75: 15 | G75: 100 | H75: 114 | I75: =G75*H75/1000000 -> 0.0114 | J75: 150 | K75: 8 | L75: 40 | M75: 102 | N75: No | O75: Natural | P75: Standard | Q75: No | R75: Paper | S75: 56 | T75: 56 | U75: 20 | V75: R-1P-15-VN | W75: FSC
B76: TT-3P-200-N | C76: Toilet Roll 3P 200Sht Nat | D76: TT | E76: 3 | F76: 15 | G76: 100 | H76: 114 | I76: =G76*H76/1000000 -> 0.0114 | J76: 200 | K76: 9 | L76: 40 | M76: 115 | N76: No | O76: Natural | P76: Standard | Q76: No | R76: Paper | S76: 40 | T76: 48 | U76: 20 | V76: R-1P-15-VN | W76: FSC
B77: TT-3P-250-N | C77: Toilet Roll 3P 250Sht Nat | D77: TT | E77: 3 | F77: 15 | G77: 100 | H77: 114 | I77: =G77*H77/1000000 -> 0.0114 | J77: 250 | K77: 10 | L77: 40 | M77: 125 | N77: No | O77: Natural | P77: Standard | Q77: No | R77: Paper | S77: 32 | T77: 44 | U77: 20 | V77: R-1P-15-VN | W77: FSC
B78: TT-3P-200-NP | C78: Toilet Roll 3P 200Sht NatPr | D78: TT | E78: 3 | F78: 15 | G78: 100 | H78: 114 | I78: =G78*H78/1000000 -> 0.0114 | J78: 200 | K78: 9 | L78: 40 | M78: 118 | N78: No | O78: Natural | P78: Deep | Q78: No | R78: Paper | S78: 40 | T78: 44 | U78: 20 | V78: R-3P-15-VNP | W78: FSC
A79: 3-PLY BAMBOO | B79: TT-3P-150-BAM | C79: Toilet Roll 3P 150Sht Bamboo | D79: TT | E79: 3 | F79: 15 | G79: 100 | H79: 114 | I79: =G79*H79/1000000 -> 0.0114 | J79: 150 | K79: 8 | L79: 40 | M79: 102 | N79: No | O79: Natural | P79: Standard | Q79: No | R79: Paper | S79: 56 | T79: 56 | U79: 20 | V79: R-3P-15-BAM | W79: FSC
B80: TT-3P-200-BAM | C80: Toilet Roll 3P 200Sht Bamboo | D80: TT | E80: 3 | F80: 15 | G80: 100 | H80: 114 | I80: =G80*H80/1000000 -> 0.0114 | J80: 200 | K80: 9 | L80: 40 | M80: 115 | N80: No | O80: Natural | P80: Standard | Q80: No | R80: Paper | S80: 40 | T80: 48 | U80: 20 | V80: R-3P-15-BAM | W80: FSC
B81: TT-3P-250-BAM | C81: Toilet Roll 3P 250Sht Bamboo | D81: TT | E81: 3 | F81: 15 | G81: 100 | H81: 114 | I81: =G81*H81/1000000 -> 0.0114 | J81: 250 | K81: 10 | L81: 40 | M81: 125 | N81: No | O81: Natural | P81: Standard | Q81: No | R81: Paper | S81: 32 | T81: 44 | U81: 20 | V81: R-3P-15-BAM | W81: FSC
B82: TT-3P-200-BMP | C82: Toilet Roll 3P 200Sht BamPr | D82: TT | E82: 3 | F82: 15 | G82: 100 | H82: 114 | I82: =G82*H82/1000000 -> 0.0114 | J82: 200 | K82: 9 | L82: 40 | M82: 118 | N82: No | O82: Natural | P82: Deep | Q82: No | R82: Paper | S82: 40 | T82: 44 | U82: 20 | V82: R-3P-15-BAMP | W82: FSC
A83: 1-PLY AFH/ JUMBO | B83: TT-1P-JR-150 | C83: Jumbo Roll 1P 150m | D83: TT | E83: 1 | F83: 18 | G83: 150000 | H83: 95 | I83: =G83*H83/1000000 -> 14.25 | J83: 1 | K83: 35 | L83: 76 | M83: 180 | N83: No | O83: White | P83: None | Q83: No | R83: None | S83: 12 | T83: 48 | U83: 20 | V83: R-1P-18-V | W83: None
B84: TT-1P-JR-200 | C84: Jumbo Roll 1P 200m | D84: TT | E84: 1 | F84: 18 | G84: 200000 | H84: 95 | I84: =G84*H84/1000000 -> 19 | J84: 1 | K84: 40 | L84: 76 | M84: 200 | N84: No | O84: White | P84: None | Q84: No | R84: None | S84: 12 | T84: 44 | U84: 20 | V84: R-1P-18-V | W84: None
B85: TT-1P-JR-250 | C85: Jumbo Roll 1P 250m | D85: TT | E85: 1 | F85: 18 | G85: 250000 | H85: 95 | I85: =G85*H85/1000000 -> 23.75 | J85: 1 | K85: 45 | L85: 76 | M85: 220 | N85: No | O85: White | P85: None | Q85: No | R85: None | S85: 12 | T85: 40 | U85: 20 | V85: R-1P-18-V | W85: None
B86: TT-1P-JR-300 | C86: Jumbo Roll 1P 300m | D86: TT | E86: 1 | F86: 18 | G86: 300000 | H86: 95 | I86: =G86*H86/1000000 -> 28.5 | J86: 1 | K86: 50 | L86: 76 | M86: 240 | N86: No | O86: White | P86: None | Q86: No | R86: None | S86: 12 | T86: 36 | U86: 20 | V86: R-1P-18-V | W86: None
B87: TT-1P-JR-400 | C87: Jumbo Roll 1P 400m | D87: TT | E87: 1 | F87: 18 | G87: 400000 | H87: 95 | I87: =G87*H87/1000000 -> 38 | J87: 1 | K87: 60 | L87: 76 | M87: 280 | N87: No | O87: White | P87: None | Q87: No | R87: None | S87: 6 | T87: 32 | U87: 20 | V87: R-1P-18-V | W87: None
B88: TT-1P-JR-500 | C88: Jumbo Roll 1P 500m | D88: TT | E88: 1 | F88: 18 | G88: 500000 | H88: 95 | I88: =G88*H88/1000000 -> 47.5 | J88: 1 | K88: 70 | L88: 76 | M88: 310 | N88: No | O88: White | P88: None | Q88: No | R88: None | S88: 6 | T88: 28 | U88: 20 | V88: R-1P-18-V | W88: None
A89: 2-PLY AFH/JUMBO | B89: TT-2P-JR-100 | C89: Jumbo Roll 2P 100m | D89: TT | E89: 2 | F89: 17 | G89: 100000 | H89: 95 | I89: =G89*H89/1000000 -> 9.5 | J89: 1 | K89: 30 | L89: 76 | M89: 170 | N89: No | O89: White | P89: Light | Q89: No | R89: None | S89: 12 | T89: 44 | U89: 20 | V89: R-1P-17-V | W89: None
B90: TT-2P-JR-150 | C90: Jumbo Roll 2P 150m | D90: TT | E90: 2 | F90: 17 | G90: 150000 | H90: 95 | I90: =G90*H90/1000000 -> 14.25 | J90: 1 | K90: 40 | L90: 76 | M90: 200 | N90: No | O90: White | P90: Light | Q90: No | R90: None | S90: 12 | T90: 40 | U90: 20 | V90: R-1P-17-V | W90: None
B91: TT-2P-JR-180 | C91: Jumbo Roll 2P 180m | D91: TT | E91: 2 | F91: 17 | G91: 180000 | H91: 95 | I91: =G91*H91/1000000 -> 17.1 | J91: 1 | K91: 45 | L91: 76 | M91: 220 | N91: No | O91: White | P91: Light | Q91: No | R91: None | S91: 12 | T91: 36 | U91: 20 | V91: R-1P-17-V | W91: None
B92: TT-2P-JR-200 | C92: Jumbo Roll 2P 200m | D92: TT | E92: 2 | F92: 17 | G92: 200000 | H92: 95 | I92: =G92*H92/1000000 -> 19 | J92: 1 | K92: 50 | L92: 76 | M92: 235 | N92: No | O92: White | P92: Light | Q92: No | R92: None | S92: 12 | T92: 32 | U92: 20 | V92: R-1P-17-V | W92: None
B93: TT-2P-JR-250 | C93: Jumbo Roll 2P 250m | D93: TT | E93: 2 | F93: 17 | G93: 250000 | H93: 95 | I93: =G93*H93/1000000 -> 23.75 | J93: 1 | K93: 55 | L93: 76 | M93: 260 | N93: No | O93: White | P93: Light | Q93: No | R93: None | S93: 6 | T93: 28 | U93: 20 | V93: R-1P-17-V | W93: None
A94: 2-PLY MINI JUMBO | B94: TT-2P-MJ-80 | C94: Mini Jumbo 2P 80m | D94: TT | E94: 2 | F94: 17 | G94: 80000 | H94: 95 | I94: =G94*H94/1000000 -> 7.6 | J94: 1 | K94: 20 | L94: 60 | M94: 130 | N94: No | O94: White | P94: Light | Q94: No | R94: None | S94: 12 | T94: 56 | U94: 20 | V94: R-1P-17-V | W94: None
B95: TT-2P-MJ-100 | C95: Mini Jumbo 2P 100m | D95: TT | E95: 2 | F95: 17 | G95: 100000 | H95: 95 | I95: =G95*H95/1000000 -> 9.5 | J95: 1 | K95: 22 | L95: 60 | M95: 145 | N95: No | O95: White | P95: Light | Q95: No | R95: None | S95: 12 | T95: 52 | U95: 20 | V95: R-1P-17-V | W95: None
B96: TT-2P-MJ-120 | C96: Mini Jumbo 2P 120m | D96: TT | E96: 2 | F96: 17 | G96: 120000 | H96: 95 | I96: =G96*H96/1000000 -> 11.4 | J96: 1 | K96: 25 | L96: 60 | M96: 160 | N96: No | O96: White | P96: Light | Q96: No | R96: None | S96: 12 | T96: 48 | U96: 20 | V96: R-1P-17-V | W96: None
B97: TT-2P-MJ-150 | C97: Mini Jumbo 2P 150m | D97: TT | E97: 2 | F97: 17 | G97: 150000 | H97: 95 | I97: =G97*H97/1000000 -> 14.25 | J97: 1 | K97: 28 | L97: 60 | M97: 175 | N97: No | O97: White | P97: Light | Q97: No | R97: None | S97: 12 | T97: 44 | U97: 20 | V97: R-1P-17-V | W97: None
A98: COMPACT/ CORELESS | B98: TT-2P-CL-700 | C98: Coreless 2P 700Sht | D98: TT | E98: 2 | F98: 17 | G98: 100 | H98: 114 | I98: =G98*H98/1000000 -> 0.0114 | J98: 700 | K98: 0 | L98: 0 | M98: 135 | N98: No | O98: White | P98: Light | Q98: No | R98: Plain | S98: 36 | T98: 48 | U98: 20 | V98: R-1P-17-V | W98: None
B99: TT-2P-CL-900 | C99: Coreless 2P 900Sht | D99: TT | E99: 2 | F99: 17 | G99: 100 | H99: 114 | I99: =G99*H99/1000000 -> 0.0114 | J99: 900 | K99: 0 | L99: 0 | M99: 150 | N99: No | O99: White | P99: Light | Q99: No | R99: Plain | S99: 36 | T99: 44 | U99: 20 | V99: R-1P-17-V | W99: None
B100: TT-2P-CL-1000 | C100: Coreless 2P 1000Sht | D100: TT | E100: 2 | F100: 17 | G100: 100 | H100: 114 | I100: =G100*H100/1000000 -> 0.0114 | J100: 1000 | K100: 0 | L100: 0 | M100: 160 | N100: No | O100: White | P100: Light | Q100: No | R100: Plain | S100: 36 | T100: 40 | U100: 20 | V100: R-1P-17-V | W100: None
...

Sheet LookUp Value
A1: EMBOSS_TYPE | B1: MULTIPLIER | C1: DESCRIPTION
A2: None | B2: 1 | C2: No embossing
A3: Light | B3: 1.03 | C3: Simple pattern, high speed
A4: Standard | B4: 1.06 | C4: Typical emboss pattern
A5: Deep | B5: 1.1 | C5: Deep emboss, slower speed
A6: Micro | B6: 1.15 | C6: Micro perf/emboss, specialized
A9: PRINT_TYPE | B9: MULTIPLIER | C9: DESCRIPTION
A10: No | B10: 1 | C10: No print on tissue
A11: Yes | B11: 1.12 | C11: Printed tissue (any)
A14: WRAP_TYPE | B14: RATE_KEY | C14: DESCRIPTION
A15: Printed | B15: Printed | C15: Uses Film_Printed_Rate
A16: Plain | B16: Plain | C16: Uses Film_Plain_Rate
A17: Paper | B17: Paper | C17: Uses Paper_Wrap rate
A18: Poly | B18: Plain | C18: Generic poly, use plain rate
A19: None | B19: None | C19: No individual wrap
A22: CATEGORY | B22: FILM_GRAMS | C22: DESCRIPTION
A23: TT | B23: 3 | C23: Toilet tissue single roll
A24: KT | B24: 12 | C24: Kitchen towel roll
A25: NAP | B25: 5 | C25: Napkin pack
A28: CERTIFICATION | B28: COST_PER_MT | C28: DESCRIPTION
A29: None | B29: 0 | C29: No certification
A30: FSC | B30: 3000 | C30: FSC chain of custody
A31: PEFC | B31: 2500 | C31: PEFC certification
A32: Food | B32: 2000 | C32: Food contact compliance
A33: FSC+Food | B33: 5000 | C33: Both FSC and Food contact
A36: DESTINATION | B36: FREIGHT_USD | C36: TRANSIT_DAYS | D36: CURRENCY
A37: USA - East Coast | B37: 3500 | C37: 30 | D37: USD
A38: USA - West Coast | B38: 2800 | C38: 22 | D38: USD
A39: Canada - Vancouver | B39: 3000 | C39: 24 | D39: CAD
A40: Canada - Toronto | B40: 4000 | C40: 35 | D40: CAD
A41: Europe - Rotterdam | B41: 2200 | C41: 22 | D41: EUR
A42: Europe - Hamburg | B42: 2400 | C42: 24 | D42: EUR
A43: UK - Felixstowe | B43: 2600 | C43: 25 | D43: GBP
A44: Middle East - Dubai | B44: 1200 | C44: 8 | D44: USD
A45: Australia-Melbourne | B45: 2000 | C45: 18 | D45: USD
A48: CORE_ID_MM | B48: COST_INR | C48: DESCRIPTION
A49: 40 | B49: 2.5 | C49: Standard toilet roll core
A50: 76 | B50: 5 | C50: AFH/industrial core
A51: 0 | B51: 0 | C51: No core (napkins, folded)

Sheet Calc Products
A1: PRODUCT COST CALCULATOR
A3: SELECT PRODUCT: | B3: TT-2P-200-R
A5: PRODUCT SPECIFICATIONS | B5: (Auto-populated)[VlookUp]
A6: Product Name | B6: =IFERROR(VLOOKUP($B$3,'Input Products'!$B:$W,2,FALSE),"SelectProduct") -> Toilet Roll 2P 200Sht Recy
A7: Category | B7: =IFERROR(VLOOKUP($B$3,'Input Products'!$B:$W,3,FALSE),"") -> TT
A8: Ply | B8: =IFERROR(VLOOKUP($B$3,'Input Products'!$B:$W,4,FALSE),"") -> 2
A9: GSM per Ply | B9: =IFERROR(VLOOKUP($B$3,'Input Products'!$B:$W,5,FALSE),"") -> 17
A10: Total GSM | B10: =B8*B9 -> 34
A11: Sheet Length (mm) | B11: =IFERROR(VLOOKUP($B$3,'Input Products'!$B:$W,6,FALSE),"") -> 100
A12: Sheet Width (mm) | B12: =IFERROR(VLOOKUP($B$3,'Input Products'!$B:$W,7,FALSE),"") -> 114
A13: Sheet Area (m²) | B13: =IFERROR(VLOOKUP($B$3,'Input Products'!$B:$W,8,FALSE),"") -> 0.0114
A14: Sheets per Unit | B14: =IFERROR(VLOOKUP($B$3,'Input Products'!$B:$W,9,FALSE),"") -> 200
A15: Core Weight (g) | B15: =IFERROR(VLOOKUP($B$3,'Input Products'!$B:$W,10,FALSE),"") -> 8
A16: Core ID (mm) | B16: =IFERROR(VLOOKUP($B$3,'Input Products'!$B:$W,11,FALSE),"") -> 40
A17: Wet Strength Required | B17: =IFERROR(VLOOKUP($B$3,'Input Products'!$B:$W,13,FALSE),"") -> No
A18: Color | B18: =IFERROR(VLOOKUP($B$3,'Input Products'!$B:$W,14,FALSE),"") -> White
A19: Emboss Type | B19: =IFERROR(VLOOKUP($B$3,'Input Products'!$B:$W,15,FALSE),"") -> Light
A20: Print | B20: =IFERROR(VLOOKUP($B$3,'Input Products'!$B:$W,16,FALSE),"") -> No
A21: Wrap Type | B21: =IFERROR(VLOOKUP($B$3,'Input Products'!$B:$W,17,FALSE),"") -> Plain
A22: Units per Carton | B22: =IFERROR(VLOOKUP($B$3,'Input Products'!$B:$W,18,FALSE),"") -> 48
A23: Cartons per Pallet | B23: =IFERROR(VLOOKUP($B$3,'Input Products'!$B:$W,19,FALSE),"") -> 60
A24: Pallets per 40HC | B24: =IFERROR(VLOOKUP($B$3,'Input Products'!$B:$W,20,FALSE),"") -> 20
A25: Matched Reel Code | B25: =IFERROR(VLOOKUP($B$3,'Input Products'!$B:$W,21,FALSE),"") -> R-1P-17-R
A26: Certification | B26: =IFERROR(VLOOKUP($B$3,'Input Products'!$B:$W,22,FALSE),"") -> None
A29: PARENT REEL DATA
A30: Reel Code | B30: =B25 -> R-1P-17-R
A31: Reel Price (INR/MT) | B31: =IFERROR(VLOOKUP($B$30,'Input Reels'!$B:$M,12,FALSE),"NoReelMatch") -> 62000
A32: Reel Price (USD/MT) | B32: =IFERROR(B31/'Input Costs'!$B$6," ") -> 676.9298
A35: FIBER MASS CALCULATION | B35: Value | C35: Formula/Notes
A36: Gross Fiber per Unit (g) | B36: =IFERROR(B8*B9*B13*B14,"") -> 77.52 | C36: =Ply × GSM × Area × Sheets
A37: Loss Factor | B37: ='Input Costs'!B54 -> 1.055 | C37: From 'Input Costs'
A38: Net Fiber Needed (g) | B38: =IFERROR(B36*B37,"") -> 81.7836 | C38: Gross × Loss Factor
A39: Core Weight (g) | B39: =B15 -> 8 | C39: From product specs
A40: Total Unit Mass (g) | B40: =IFERROR(B38+B39,"") -> 89.7836 | C40: Fiber + Core
A41: Units per MT | B41: =1000000/B40 -> 11137.892 | C41: How many units from 1 MT
A43: COST CALCULATION | B43: INR per Unit | C43: USD per Unit
A45: 1. REEL/FIBER COST
A46: Reel Price (INR/MT) | B46: =B38 -> 81.7836 | C46: From Reel Lookup (Row 38)
A47: Fiber cost per unit | B47: =IFERROR((B37/1000000)*B46,"") -> 8.6281698e-05 | C47: =IFERROR(B47/'Input Costs'!$B$6," ") -> 9.4204278e-07
A49: 2. CORE COST
A50: Core cost per unit | B50: =IFERROR(VLOOKUP(B16,'LookUp Value'!$A$49:$B$51,2,FALSE),0) -> 2.5 | C50: =IFERROR(B50/'Input Costs'!$B$6,"") -> 0.027295556
A52: 3. CONVERTING COST
A53: Base converting per MT | B53: =IFERROR('Input Costs'!$B$18,"") -> 16800 | C53: From 'Input Costs'
A54: Emboss multiplier | B54: =IFERROR(VLOOKUP(B19,'LookUp Value'!$A$2:$B$6,2,FALSE),1) -> 1 | C54: From LOOKUP_Tables
A55: Print multiplier | B55: =IFERROR(VLOOKUP(B20,'LookUp Value'!$A$10:$B$11,2,FALSE),1) -> 1 | C55: From LOOKUP_Tables
A56: Combined multiplier | B56: =B54*B55 -> 1 | C56: Emboss × Print
A57: Adjusted converting/MT | B57: =IFERROR(B56*B54,"") -> 1 | C57: Base × Combined
A58: Converting per unit | B58: =IFERROR(B57/B41,"") -> 8.97836e-05 | C58: =IFERROR(B57/'Input Costs'!$B$6,"") -> 0.010918223
A60: 4. PACKAGING COST
A61: Film rate (INR/kg) | B61: =IF(B20="Yes",'Input Costs'!$B$21,IF(B20="No",0,'Input Costs'!$B$22)) -> 0 | C61: Based on wrap type
A62: Film grams per unit | B62: =IFERROR(VLOOKUP(B7,'LookUp Value'!$A$23:$B$25,2,FALSE),5) -> 5 | C62: By category
A63: Film cost per unit | B63: =IFERROR((B62/1000)*B61,"") -> 0 | C63: =IFERROR(B63/'Input Costs'!$B$6,"") -> 0
A64: Carton cost per unit | B64: =IFERROR('Input Costs'!$B$24/B23,"") -> 0.66666667 | C64: =IFERROR(B64/'Input Costs'!$B$6,"") -> 0.007278815
A65: Tape & Label per unit | B65: =IFERROR(('Input Costs'!$B$25+'Input Costs'!$B$26)/B23,"") -> 0.083333333 | C65: =IFERROR(B65/'Input Costs'!$B$6,"") -> 0.00090985188
A66: Pallet cost per unit | B66: =IFERROR(('Input Costs'!$B$27+'Input Costs'!$B$28)/(B23*B24),"") -> 0.51666667 | C66: =IFERROR(B66/'Input Costs'!$B$6,"") -> 0.0056410816
A67: Total packaging per unit | B67: =IFERROR(SUM(B63:B66),"") -> 1.2666667 | C67: =IFERROR(B67/'Input Costs'!$B$6,"") -> 0.013829749
A69: 5. OVERHEAD COST
A70: Overhead per MT | B70: =IFERROR('Input Costs'!$B$47,"") -> 6650 | C70: From 'Input Costs'
A71: Overhead per unit | B71: =IFERROR(B70/B41,"") -> 0.59706094 | C71: =IFERROR(B71/'Input Costs'!$B$6,"") -> 0.0065188442
A73: 6. CERTIFICATION COST
A74: Certification per MT | B74: =IFERROR(VLOOKUP(B26,'LookUp Value'!$A$29:$B$33,2,FALSE),0) -> 0 | C74: From LOOKUP_Tables
A75: Certification per unit | B75: =IFERROR(B74/B41,"") -> 0 | C75: =IFERROR(B75/'Input Costs'!$B$6,"") -> 0
A78: EX-WORKS COST SUMMARY | B78: INR | C78: USD | D78: % of Cost
A79: Fiber/Reel Cost | B79: =B47 -> 8.6281698e-05 | C79: =C47 -> 9.4204278e-07 | D79: =B79/$B$85 -> 2.2905575e-05
A80: Core Cost | B80: =B50 -> 2.5 | C80: =C50 -> 0.027295556 | D80: =B80/$B$85 -> 0.66368579
A81: Converting Cost | B81: =B58 -> 8.97836e-05 | C81: =C58 -> 0.010918223 | D81: =B81/$B$85 -> 2.383524e-05
A82: Packaging Cost | B82: =B67 -> 1.2666667 | C82: =C67 -> 0.013829749 | D82: =B82/$B$85 -> 0.33626747
A83: Overhead Cost | B83: =B71 -> 0.59706094 | C83: =C71 -> 0.0065188442 | D83: =B83/$B$85 -> 0.15850434
A84: Certification Cost | B84: =B75 -> 0 | C84: =C75 -> 0 | D84: =B84/$B$85 -> 0
A85: TOTAL EX-WORKS COST | B85: =SUM(B78:B82) -> 3.7668427 | C85: =SUM(C78:C82) -> 0.052044469 | D85: 1
A88: ALTERNATE UNITS | B88: INR | C88: USD
A89: Cost per Carton | B89: =B85*B22 -> 180.80845 | C89: =C85*B22 -> 2.4981345
A90: Cost per Pallet | B90: =B89*B23 -> 10848.507 | C90: =C89*B23 -> 149.88807
A91: Cost per 40HC Container | B91: =B90*B24 -> 216970.14 | C91: =C90*B24 -> 2997.7614
A92: Cost per MT | B92: =B85*B41 -> 41954.686 | C92: =C85*B41 -> 579.66566
A94: PRICING WITH MARGIN | B94: INR | C94: USD
A95: At 10% Margin | B95: =B85/(1-0.1) -> 4.1853808 | C95: =C85/(1-0.1) -> 0.057827188
A96: At 15% Margin | B96: =B85/(1-0.15) -> 4.4315797 | C96: =C85/(1-0.15) -> 0.061228787
A97: At 20% Margin | B97: =B85/(1-0.2) -> 4.7085534 | C97: =C85/(1-0.2) -> 0.065055587
A98: At 25% Margin | B98: =B85/(1-0.25) -> 5.022457 | C98: =C85/(1-0.25) -> 0.069392626

Sheet Calc Export
A1: EXPORT LANDED COST CALCULATOR
A3: INPUTS
A4: Product Code | B4: ='Calc Products'!B3 -> TT-2P-200-R
A5: Product Name | B5: ='Calc Products'!B6 -> Toilet Roll 2P 200Sht Recy
A6: Destination | B6: Canada - Vancouver
A7: Quantity (units) | B7: 100000
A8: Incoterm | B8: FOB
A10: SHIPMENT CALCULATION
A11: Units ordered | B11: =B7 -> 100000 | C11: From input above
A12: Units per carton | B12: ='Calc Products'!B22 -> 48 | C12: From CALC_Product
A13: Cartons needed | B13: =IFERROR(ROUNDUP(B11/B12,0),"") -> 2084 | C13: Rounded up
A14: Cartons per pallet | B14: ='Calc Products'!B23 -> 60 | C14: From CALC_Product
A15: Pallets needed | B15: =IFERROR(ROUNDUP(B13/B14,0),"") -> 35 | C15: Rounded up
A16: Pallets per 40HC | B16: ='Calc Products'!B24 -> 20 | C16: From CALC_Product
A17: Containers needed | B17: =IFERROR(ROUNDUP(B15/B16,0),"") -> 2 | C17: Rounded up
A18: Container utilization | B18: =IFERROR(B15/(B17*B16),"") -> 0.875 | C18: Format as %
A19: Actual units shipped | B19: =IFERROR(B13*B12,"") -> 100032 | C19: May differ due to rounding
A20: Excess units | B20: =IFERROR(B19-B11,"") -> 32 | C20: Extra units in shipment
A22: COST BUILDUP | B22: INR | C22: USD
A24: EX-WORKS VALUE
A25: Ex-works cost per unit | B25: ='Calc Products'!B85 -> 3.7668427 | C25: ='Calc Products'!C85 -> 0.052044469
A26: Total ex-works value | B26: =IFERROR(B25*B19,"") -> 376804.81 | C26: =IFERROR(C25*B19,"") -> 5206.1124
A28: LOCAL LOGISTICS
A29: Factory to port | B29: =IFERROR('Input Costs'!$B$58*B17,"") -> 70000 | C29: =IFERROR(B29/'Input Costs'!$B$6,"") -> 764.27558
A30: Port handling | B30: =IFERROR('Input Costs'!$B$59*B17,"") -> 50000 | C30: =IFERROR(B30/'Input Costs'!$B$6,"") -> 545.91113
A31: Documentation | B31: =IFERROR('Input Costs'!$B$60,"") -> 15000 | C31: =IFERROR(B31/'Input Costs'!$B$6,"") -> 163.77334
A32: Export customs | B32: =IFERROR('Input Costs'!$B$61,"") -> 10000 | C32: =IFERROR(B32/'Input Costs'!$B$6,"") -> 109.18223
A33: Certificates | B33: =IFERROR('Input Costs'!$B$62,"") -> 5000 | C33: =IFERROR(B33/'Input Costs'!$B$6,"") -> 54.591113
A34: Total local logistics | B34: =IFERROR(SUM(B29:B33),"") -> 150000 | C34: =IFERROR(SUM(C29:C33),"") -> 1637.7334
A36: FOB VALUE | B36: =IFERROR(B26+B34,"") -> 526804.81 | C36: =IFERROR(C26+C34,"") -> 6843.8457
A38: INTERNATIONAL FREIGHT
A39: Freight rate per 40HC (USD) | B39: =IFERROR(VLOOKUP(B6,'LookUp Value'!$A$37:$B$45,2,FALSE),"") -> 3000 | C39: (Same as B39)
A40: Freight rate per 40HC (INR) | B40: =IFERROR(B39*'Input Costs'!$B$6,"") -> 274770 | C40: =B39 -> 3000
A41: Total ocean freight | B41: =IFERROR(B40*B17,"") -> 549540 | C41: =IFERROR(C40*B17,"") -> 6000
A42: Marine insurance | B42: =IFERROR(B36*'Input Costs'!$B$76,"") -> 2107.2192 | C42: =IFERROR(C36*'Input Costs'!$B$76,"") -> 27.375383
A43: Total freight & insurance | B43: =IFERROR(B41+B42,"") -> 551647.22 | C43: =IFERROR(C41+C42,"") -> 6027.3754
A45: CIF VALUE | B45: =IFERROR(B36+B43,"") -> 1078452 | C45: =IFERROR(C36+C43,"") -> 12871.221
A47: DESTINATION COSTS (if DAP)
A48: Import duty estimate | B48: 0 | C48: 0
A49: Customs clearance | B49: 0 | C49: 0
A50: Destination delivery | B50: 0 | C50: 0
A51: Total destination costs | B51: =IFERROR(SUM(B48:B50),"") -> 0 | C51: =IFERROR(SUM(C48:C50),"") -> 0
A53: DAP VALUE | B53: =IFERROR(B45+B51,"") -> 1078452 | C53: =IFERROR(C45+C51,"") -> 12871.221
A56: LANDED COST SUMMARY
A59: Selected Incoterm | B59: =B8 -> FOB
A60: Landed Value (total) | B60: =IF(B8="FOB",B36,IF(B8="CIF",B45,B53)) -> 526804.81 | C60: =IF(B8="FOB",C36,IF(B8="CIF",C45,C53)) -> 6843.8457
A62: COST BREAKDOWN | B62: INR | C62: USD
A63: Per unit | B63: =IFERROR(B60/B19,"") -> 5.2663629 | C63: =IFERROR(C60/B19,"") -> 0.068416564
A64: Per carton | B64: =IFERROR(B63*B12,"") -> 252.78542 | C64: =IFERROR(C63*B12,"") -> 3.2839951
A65: Per pallet | B65: =IFERROR(B64*B14,"") -> 15167.125 | C65: =IFERROR(C64*B14,"") -> 197.0397
A66: Per container | B66: =IFERROR(B60/B17,"") -> 263402.41 | C66: =IFERROR(C60/B17,"") -> 3421.9229
A68: PRICING WITH MARGIN | B68: INR per Unit | C68: USD per Unit
A69: At 10% Margin | B69: =IFERROR(B63/(1-0.1),"") -> 5.8515143 | C69: =IFERROR(C63/(1-0.1),"") -> 0.076018405
A70: At 15% Margin | B70: =IFERROR(B63/(1-0.15),"") -> 6.195721 | C70: =IFERROR(C63/(1-0.15),"") -> 0.080490075
A71: At 20% Margin | B71: =IFERROR(B63/(1-0.2),"") -> 6.5829536 | C71: =IFERROR(C63/(1-0.2),"") -> 0.085520705
A72: At 25% Margin | B72: =IFERROR(B63/(1-0.25),"") -> 7.0218172 | C72: =IFERROR(C63/(1-0.25),"") -> 0.091222085
A74: CARTON PRICING WITH MARGIN | B74: INR per Carton | C74: USD per Carton
A75: At 10% Margin | B75: =IFERROR(B69*B12,"") -> 280.87269 | C75: =IFERROR(C69*B12,"") -> 3.6488834
A76: At 15% Margin | B76: =IFERROR(B70*B12,"") -> 297.39461 | C76: =IFERROR(C70*B12,"") -> 3.8635236
A77: At 20% Margin | B77: =IFERROR(B71*B12,"") -> 315.98177 | C77: =IFERROR(C71*B12,"") -> 4.1049938
A78: At 25% Margin | B78: =IFERROR(B72*B12,"") -> 337.04722 | C78: =IFERROR(C72*B12,"") -> 4.3786601
A80: PALLET PRICING WITH MARGIN | B80: INR per Pallet | C80: USD per Pallet
A81: At 10% Margin | B81: =IFERROR(B75*B14,"") -> 16852.361 | C81: =IFERROR(C75*B14,"") -> 218.93301
A82: At 15% Margin | B82: =IFERROR(B76*B14,"") -> 17843.677 | C82: =IFERROR(C76*B14,"") -> 231.81142
A83: At 20% Margin | B83: =IFERROR(B77*B14,"") -> 18958.906 | C83: =IFERROR(C77*B14,"") -> 246.29963
A84: At 25% Margin | B84: =IFERROR(B78*B14,"") -> 20222.833 | C84: =IFERROR(C78*B14,"") -> 262.71961
A86: CONTAINER PRICING WITH MARGIN | B86: INR per 40HC | C86: USD per 40HC
A87: At 10% Margin | B87: =IFERROR(B69*B12*B14*B16,"") -> 337047.22 | C87: =IFERROR(C69*B12*B14*B16,"") -> 4378.6601
A88: At 15% Margin | B88: =IFERROR(B70*B12*B14*B16,"") -> 356873.53 | C88: =IFERROR(C70*B12*B14*B16,"") -> 4636.2283
A89: At 20% Margin | B89: =IFERROR(B71*B12*B14*B16,"") -> 379178.13 | C89: =IFERROR(C71*B12*B14*B16,"") -> 4925.9926
A90: At 25% Margin | B90: =IFERROR(B72*B12*B14*B16,"") -> 404456.67 | C90: =IFERROR(C72*B12*B14*B16,"") -> 5254.3921
A92: SHIPMENT DETAILS
A93: Transit time (days) | B93: =IFERROR(VLOOKUP(B6,'LookUp Value'!$A$37:$C$45,3,FALSE),"") -> 24 | C93: From Destinations table
A94: Estimated departure | B94: =TODAY()+7 -> 46069 | C94: Assumes 7 days to prepare
A95: Estimated arrival | B95: =IFERROR(B94+B93,"") -> 46093 | C95: Departure + Transit
A97: WEIGHT & VOLUME
A98: Unit weight (g) | B98: ='Calc Products'!$B$40 -> 89.7836 | C98: From CALC_Product
A99: Total weight (kg) | B99: =IFERROR((B98*B19)/1000,"") -> 8981.2331 | C99: Units × Weight ÷ 1000
A100: Total weight (MT) | B100: =IFERROR(B99/1000,"") -> 8.9812331 | C100: Kg ÷ 1000
A101: Weight per container (MT) | B101: =IFERROR(B100/B17,"") -> 4.4906165 | C101: Total ÷ Containers
A103: COST ANALYSIS
A104: Ex-works % of total | B104: =IFERROR(B26/B60,"") -> 0.71526456 | C104: Format as %
A105: Local logistics % of total | B105: =IFERROR(B34/B60,"") -> 0.28473544 | C105: Format as %
A106: Freight % of total | B106: =IFERROR(B43/B60,"") -> 1.0471568 | C106: Format as %
A107: Freight cost per MT | B107: =IFERROR(B41/B100,"") -> 61187.589 | C107: INR per MT shipped
A108: Freight cost per MT (USD) | B108: =IFERROR(B107/'Input Costs'!$B$6,"") -> 668.05971 | C108: USD per MT shipped

Sheet Quote Summary
A1: COMPANY HEADER
A2: [YOUR COMPANY NAME]
A3: [Address Line 1]
A4: [City, State, PIN Code]
A5: [Phone: +91-XXXX-XXXXXX]
A6: [Email: sales@company.com]
A7: QUOTATION
A8: Quote Date: | B8: =TODAY() -> 46062
A9: Valid Until: | B9: =B8+30 -> 46092
A10: Quote Reference: | B10: ="Q-"&TEXT(B8,"YYMMDD")&"-"&LEFT('Calc Export'!$B$4,10) -> Q-260209- TT-2P-200
A11: CUSTOMER DETAILS
A12: Customer Name: | B12: [Type Customer Name Here]
A13: Contact Person: | B13: [Type Contact Person Here]
A14: Email: | B14: [Type Email Here]
A15: Phone: | B15: [Type Phone Here]
A16: Destination: | B16: ='Calc Export'!$B$6 -> Canada - Vancouver
A17: PRODUCT DETAILS
A18: Product Code: | B18: ='Calc Products'!$B$3 -> TT-2P-200-R
A19: Product Description: | B19: ='Calc Products'!$B$6 -> Toilet Roll 2P 200Sht Recy
A20: Ply: | B20: ='Calc Products'!$B$8 -> 2
A21: GSM (Total): | B21: ='Calc Products'!B10 -> 34
A22: Specifications: | B22: =B20&"-Ply, "&B21&" GSM Total" -> 2-Ply, 34 GSM Total
A23: Color: | B23: ='Calc Products'!$B$18 -> White
A24: Sheets per Unit: | B24: ='Calc Products'!B14 -> 200
A25: Emboss: | B25: ='Calc Products'!B19 -> Light
A26: Certification: | B26: ='Calc Products'!B26 -> None
A27: PACKAGING DETAILS
A28: Units per Carton: | B28: ='Calc Products'!$B$22 -> 48
A29: Cartons per Pallet: | B29: ='Calc Products'!$B$23 -> 60
A30: Pallets per 40'HC: | B30: ='Calc Products'!$B$24 -> 20
A31: Units per Pallet: | B31: =B28*B29 -> 2880
A32: Units per Container: | B32: =B31*B30 -> 57600
A33: ORDER QUANTITY
A34: Units Ordered: | B34: ='Calc Export'!$B$7 -> 100000
A35: Actual Units (shipped): | B35: ='Calc Export'!$B$19 -> 100032
A36: Cartons: | B36: ='Calc Export'!$B$13 -> 2084
A37: Pallets: | B37: ='Calc Export'!$B$15 -> 35
A38: 40'HC Containers: | B38: ='Calc Export'!$B$17 -> 2
A39: Container Utilization: | B39: ='Calc Export'!$B$18 -> 0.875 | C39: Format as %
A40: PRICING
A41: Incoterm: | B41: ='Calc Export'!$B$8 -> FOB
A42: Destination: | B42: ='Calc Export'!$B$6 -> Canada - Vancouver
B43: Per Unit | C43: Per Carton | D43: Per Pallet
A44: Cost (USD): | B44: ='Calc Export'!$C$63 -> 0.068416564 | C44: ='Calc Export'!$C$64 -> 3.2839951 | D44: ='Calc Export'!$C$65 -> 197.0397
A45: Selling Price (USD):
A46: At 15% Margin | B46: ='Calc Export'!$C$70 -> 0.080490075 | C46: ='Calc Export'!$C$76 -> 3.8635236 | D46: =IFERROR(C46*B29,"") -> 231.81142
A47: At 20% Margin | B47: ='Calc Export'!$C$71 -> 0.085520705 | C47: ='Calc Export'!$C$77 -> 4.1049938 | D47: =IFERROR(C47*B29,"") -> 246.29963
A48: At 25% Margin | B48: ='Calc Export'!$C$72 -> 0.091222085 | C48: ='Calc Export'!$C$78 -> 4.3786601 | D48: =IFERROR(C48*B29,"") -> 262.71961
A49: SELECTED PRICE (20% Margin): | B49: =B47 -> 0.085520705 | C49: =C47 -> 4.1049938 | D49: =D47 -> 246.29963
A50: ORDER VALUE SUMMARY
B51: USD | C51: INR
A52: Total Order Value: | B52: =IFERROR(B49*B35,"") -> 8554.8072 | C52: =IFERROR(B52*'Input Costs'!$B$6,"") -> 783534.79
A53: Per Container Value: | B53: =IFERROR(B52/B38,"") -> 4277.4036 | C53: =IFERROR(C52/B38,"") -> 391767.39
A54: SHIPMENT DETAILS
A55: Estimated Transit Time: | B55: =IFERROR(VLOOKUP(B42,'LookUp Value'!$A$37:$C$45,3,FALSE),"")&" days" -> 24 days
A56: Estimated Weight (MT): | B56: =IFERROR('Calc Export'!$B$100,"") -> 8.9812331
A57: TERMS & CONDITIONS
A58: Payment Terms: | B58: 30% Advance, 70% Against B/L Copy
A59: Delivery Time: | B59: 4-6 weeks from order confirmation
A60: Validity: | B60: ="Prices valid until "&TEXT(B12,"DD-MMM-YYYY")
A61: Minimum Order: | B61: 1 x 40'HC Container
A62: NOTES
A63: 1 | B63: Prices are subject to change based on raw material fluctuations
A64: 2 | B64: Delivery dates are estimates and subject to vessel availability
A65: 3 | B65: Custom packaging/branding available at additional cost
A66: 4 | B66: Quality certifications available upon request
A67: For queries, please contact:
A68: Name: [Sales Contact Name] | B68: Email: [sales@company.com] | C68: Phone: [+91-XXXX-XXXXXX]
